Thông tư Quy định điều kiện, trình tự ngừng, giảm mức cung cấp điện

Căn_cứ <NĐ rel="Pursuant"> Nghị_định số 95/2012/NĐ-CP ngày 12 tháng 11 năm 2012 </NĐ> của Chính_phủ quy_định chức_năng , nhiệm_vụ , quyền_hạn và cơ_cấu tổ_chức của Bộ Công_Thương ;
Căn_cứ <L rel="Pursuant"> Luật Điện_lực ngày 03 tháng 12 năm 2004 </L> và <L rel="Pursuant"> Luật sửa_đổi , bổ_sung một_số Điều của <L rel="Others"> Luật Điện_lực </L> ngày 20 tháng 11 năm 2012 </L> ;
Căn_cứ <NĐ rel="Pursuant"> Nghị_định số 137/2013/NĐ-CP ngày 21 tháng 10 năm 2013 </NĐ> của Chính_phủ quy_định chi_tiết thi_hành một_số điều của <L rel="Others"> Luật Điện_lực </L> và <L rel="Others"> Luật sửa_đổi , bổ_sung một_số điều của <L rel="Others"> Luật Điện_lực </L> </L> ;
Điều 1 .  Phạm_vi điều_chỉnh 

Thông_tư này quy_định các điều_kiện ngừng , giảm mức cung_cấp điện ;  trình_tự ngừng , giảm mức cung_cấp điện trong hoạt_động điện_lực . 

Điều 2 .  Đối_tượng áp_dụng 

1 . Tập_đoàn Điện_lực Việt_Nam . 

2 . Tổng_công_ty Điện_lực . 

3 . Công_ty Điện_lực ( thuộc Tổng_công_ty Điện_lực ) . 

4 . Đơn_vị phân_phối và bán_lẻ điện . 

5 . Khách_hàng sử_dụng điện . 

6 . Tổ_chức , cá_nhân có liên_quan . 

Điều 3 .  Giải_thích từ_ngữ 

1 . Bến bán điện là đơn_vị điện_lực được cấp giấy_phép hoạt_động điện_lực trong lĩnh_vực phân_phối và bán_lẻ điện , bao_gồm : 

a ) Tổng_công_ty Điện_lực ; 

b ) Công_ty Điện_lực ( thuộc Tổng_công_ty Điện_lực ) ; 

c ) Đơn_vị phân_phối và bán_lẻ điện . 

2 . Bên mua điện là tổ_chức , cá_nhân mua điện để sử_dụng hoặc để bán_lẻ điện cho khách_hàng sử_dụng điện , bao_gồm : 

a ) Đơn_vị phân_phối và bán_lẻ điện ; 

b ) Khách_hàng sử_dụng điện . 

3 . Đơn_vị phân_phối và bán_lẻ điện là đơn_vị điện_lực được cấp giấy_phép hoạt_động điện_lực trong lĩnh_vực phân_phối và bán_lẻ điện để bán điện cho khách_hàng sử_dụng điện . 

4 . Giảm mức cung_cấp điện là việc giảm cung_cấp công_suất , sản_lượng điện so với mức công_suất , sản_lượng đã thỏa_thuận trong hợp_đồng mua_bán điện đã ký . 

5 . Khách_hàng sử_dụng điện là tổ_chức , cá_nhân mua điện để sử_dụng , không bán lại cho tổ_chức , cá_nhân khác . 

6 . Khách_hàng sử_dụng điện quan_trọng là khách_hàng thuộc diện ưu_tiên cấp điện khi bên bán điện thực_hiện ngừng , giảm mức cung_cấp điện , được Ủy_ban nhân_dân tỉnh , thành_phố trực_thuộc Trung_ương xác_định căn_cứ vào tầm quan_trọng về chính_trị , xã_hội , an_ninh , quốc_phòng . 

7 . Sự_kiện bất_khả_kháng là sự_kiện xảy ra một_cách khách_quan mà bên bán điện không_thể kiểm_soát được , không_thể lường trước được và không_thể khắc_phục được mặc_dù đã áp_dụng mọi biện_pháp cần_thiết và khả_năng cho phép . 

Điều 4 .  Thông_báo ngừng , giảm mức cung_cấp điện 

1 . Mọi trường_hợp ngừng , giảm mức cung_cấp điện , bên bán điện phải thông_báo trước cho bên mua điện , trừ trường_hợp quy_định tại Khoản 6 Điều 7 <L rel="Reference"> Luật Điện_lực </L> ( hành_vi trộm_cắp điện dưới mọi hình_thức ) và Điều 6 Thông_tư này .
2 . Nội_dung thông_báo ngừng cấp điện hoặc giảm mức cung_cấp điện bao_gồm : 

a ) Địa_điểm ngừng cấp điện hoặc giảm mức cung_cấp điện ; 

b ) Lý_do ngừng cấp điện hoặc giảm mức cung_cấp điện ; 

c ) Thời_gian bắt_đầu ngừng cấp điện hoặc giảm mức cung_cấp điện ; 

d ) Thời_gian dự_kiến đóng điện_trở_lại hoặc bảo_đảm mức cung_cấp điện bình_thường . 

3 . Thông_báo ngừng , giảm mức cung_cấp điện được thực_hiện bằng một trong các hình_thức : văn_bản , điện_báo , điện_thoại , fax , tin nhắn ( SMS ) , thư điện_tử ( Email ) , các phương_tiện thông_tin đại_chúng do hai bên thỏa_thuận và ghi trong hợp_đồng mua_bán điện . 

4 . Người của bên bán điện ký thông_báo ngừng , giảm mức cung_cấp điện phải là một trong những người sau : 

a ) Người đại_diện hoặc người được ủy_quyền theo quy_định của pháp_luật ; 

b ) Người được ủy_quyền ký thông_báo ngừng , giảm cung_cấp điện do hai bên thỏa_thuận trong hợp_đồng mua_bán điện . 

Điều 5 .  Ngừng , giảm mức cung_cấp điện không khẩn_cấp 

1 . Ngừng , giảm mức cung_cấp điện theo kế_hoạch của bên bán điện khi có nhu_cầu sửa_chữa , bảo_dưỡng , đại_tu , xây_lắp các công_trình điện , điều hòa , hạn_chế phụ_tải do thiếu điện và các nhu_cầu khác theo kế_hoạch . 

2 . Ngừng cấp điện theo yêu_cầu của tổ_chức , cá_nhân có liên_quan trong trường_hợp để đảm_bảo an_toàn phục_vụ thi_công các công_trình . 

3 . Ngừng , giảm mức cung_cấp điện theo yêu_cầu của bên mua điện . 

Điều 6 .  Ngừng , giảm mức cung_cấp điện khẩn_cấp 

1 . Do có sự_cố xảy ra trên lưới_điện cấp điện cho bên mua điện ;  sự_cố trong hệ_thống điện gây mất điện mà bên bán điện không kiểm_soát được . 

2 . Có nguy_cơ gây sự_cố , mất an_toàn nghiêm_trọng cho người , thiết_bị và hệ_thống điện . 

3 . Do hệ_thống điện thiếu công_suất dẫn đến đe_dọa sự an_toàn của hệ_thống điện . 

4 . Do sự_kiện bất_khả_kháng . 

Điều 7 .  Ngừng cấp điện do tổ_chức , cá_nhân vi_phạm_quy_định của pháp_luật 

1 . Bên mua điện có hành_vi vi_phạm_quy_định tại : 

a ) Các Khoản 1 , 4 , 5 , 6 , 7 và Khoản 8 Điều 7 <L rel="Reference"> Luật Điện_lực </L> ( Các hành_vi bị cấm trong hoạt_động điện_lực và sử_dụng điện ) .
b ) Điểm a và Điểm b Khoản 2 Điều 46 ; Điểm b và Điểm_c Khoản 2 Điều 47 <L rel="Reference"> Luật Điện_lực </L> .
2 . Bên mua điện không thực_hiện thanh_toán tiền điện theo quy_định tại Khoản 9 Điều 1 <L rel="Reference"> Luật sửa_đổi , bổ_sung một_số điều của <L rel="Others"> Luật Điện_lực </L> </L> .
3 . Theo yêu_cầu của cơ_quan nhà_nước có thẩm_quyền trong trường_hợp tổ_chức , cá_nhân vi_phạm_quy_định của <L rel="Reference"> Luật Điện_lực </L> , <L rel="Reference"> Luật Xây_dựng </L> , pháp_luật về bảo_vệ môi_trường .
4 . Bên mua điện không thực_hiện biện_pháp bảo_đảm thực_hiện hợp_đồng , không duy_trì biện_pháp bảo_đảm thực_hiện hợp_đồng theo quy_định tại Điều 12 <NĐ rel="Reference"> Nghị_định số 137/2013/NĐ-CP ngày 21 tháng 10 năm 2013 </NĐ> của Chính_phủ quy_định chi_tiết thi_hành một_số điều của <L rel="Others"> Luật Điện_lực </L> và <L rel="Others"> Luật sửa_đổi , bổ_sung một_số điều của <L rel="Others"> Luật Điện_lực </L> </L> .
Điều 8 .  Trình_tự ngừng , giảm mức cung_cấp điện không khẩn_cấp 

1 . Trường_hợp ngừng , giảm mức cung_cấp điện không khẩn_cấp , bên bán điện phải thông_báo cho bên mua điện biết trước thời_điểm ngừng , giảm mức cung_cấp điện ít_nhất 05 ngày , cụ_thể như sau : 

a ) Gửi thông_báo bằng văn_bản hoặc thông_báo bằng hình_thức khác đã được hai bên thỏa_thuận trong hợp_đồng mua_bán điện cho khách_hàng sử_dụng điện trung_bình trên 100.000 kWh/tháng và khách_hàng sử_dụng điện quan_trọng biết ; 

b ) Thông_báo trong 03 ngày liên_tiếp trên phương_tiện thông_tin đại_chúng đối_với các tổ_chức , cá_nhân sử_dụng điện còn lại . 

2 . Sau khi thông_báo ngừng , giảm mức cung_cấp điện , bên bán điện có trách_nhiệm tiến_hành ngừng , giảm mức cung_cấp điện theo đúng nội_dung đã thông_báo . 

Trường_hợp không thực_hiện ngừng , giảm mức cung_cấp điện theo nội_dung đã thông_báo , bên bán điện có trách_nhiệm thông_báo lại cho bên mua điện trước thời_điểm ngừng , giảm cung_cấp điện đã thông_báo ít_nhất 24 giờ . 

3 . Trường_hợp bên mua điện có đề_nghị thay_đổi thời_gian ngừng , giảm mức cung_cấp điện đã được thông_báo thì phải trao_đổi với bên bán điện trước thời_điểm ngừng , giảm mức cung_cấp điện ít_nhất 48 giờ .  Bên bán điện có trách_nhiệm xem_xét , giải_quyết hợp_lý đề_nghị của bên mua điện , cụ_thể như sau : 

a ) Trường_hợp không_thể thay_đổi việc ngừng , giảm mức cung_cấp điện , bên bán điện vẫn được ngừng , giảm mức cung_cấp điện theo kế_hoạch nhưng phải thông_báo lại cho bên mua điện và nêu rõ lý_do trước thời_điểm ngừng , giảm mức cung_cấp điện đã thông_báo ít_nhất 24 giờ ; 

b ) Trường_hợp chấp_nhận thay_đổi thời_gian ngừng , giảm mức cung_cấp điện , bên bán điện phải thông_báo trước cho bên mua điện trước thời_điểm ngừng , giảm mức cung_cấp điện đã thông_báo ít_nhất 24 giờ . 

4 . Sau khi tiến_hành ngừng , giảm mức cung_cấp điện , bên bán điện phải ghi đầy_đủ thời_gian , nội_dung , trình_tự thao_tác ngừng , giảm mức cung_cấp điện vào_sổ nhật_ký công_tác hoặc nhật_ký vận_hành . 

5 . Bên bán điện phải cấp điện_trở_lại theo đúng thời_hạn đã thông_báo .  Trường_hợp thời_gian cấp điện_trở_lại bị chậm so với thời_gian đã thông_báo từ 01 giờ trở lên , bên bán điện phải thông_báo cho khách_hàng sử_dụng điện trung_bình trên 100.000 kWh/tháng và khách_hàng sử_dụng điện quan_trọng biết thời_gian cấp điện_trở_lại bằng điện_thoại hoặc hình_thức thông_báo khác do hai bên thỏa_thuận trong hợp_đồng mua_bán điện . 

6 . Việc ngừng hoặc cấp điện_trở_lại đối_với các trường_hợp quy_định tại Khoản 2 và Khoản 3 Điều 5 Thông_tư này chỉ tiến_hành sau khi bên yêu_cầu ngừng cấp điện đã thanh_toán đủ cho bên bán điện các chi_phí liên_quan đến việc ngừng và cấp điện_trở_lại . 

Điều 9 .  Trình_tự ngừng , giảm mức cung_cấp điện khẩn_cấp 

1 . Xác_định nguyên_nhân , phạm_vi ảnh_hưởng , thời_gian dự_kiến cấp điện_trở_lại . 

2 . Thông_báo cho bên mua điện biết theo hình_thức thông_báo đã được hai bên thỏa_thuận trong hợp_đồng mua_bán điện , bao_gồm các nội_dung quy_định tại Khoản 1 Điều này trong thời_hạn 24 giờ kể từ thời_điểm thực_hiện ngừng , giảm mức cung_cấp điện khẩn_cấp . 

3 . Bên bán điện phải ghi đầy_đủ thời_gian , nguyên_nhân , trình_tự thao_tác ngừng , giảm mức cung_cấp điện vào_sổ nhật_ký công_tác hoặc nhật_ký vận_hành . 

4 . Trường_hợp ngừng , giảm mức cung_cấp điện do hệ_thống điện thiếu công_suất dẫn đến đe_dọa sự an_toàn của hệ_thống điện , bên bán điện phải đảm_bảo thực_hiện cắt , giảm đúng lượng công_suất phụ_tải được tính_toán và phân_bổ theo quy_định về việc lập và thực_hiện kế_hoạch cung_ứng điện khi hệ_thống điện quốc_gia thiếu nguồn điện . 

5 . Phối_hợp với các bên có liên_quan khẩn_trương khắc_phục các nguyên_nhân dẫn đến ngừng , giảm mức cung_cấp điện khẩn_cấp để cấp điện_trở_lại trong thời_gian nhanh nhất . 

Điều 10 .  Trình_tự ngừng cấp điện do tổ_chức , cá_nhân vi_phạm_quy_định của pháp_luật 

1 . Đối_với trường_hợp quy_định tại Khoản 1 Điều 7 Thông_tư này 

a ) Trường_hợp bên mua điện thực_hiện_hành_vi quy_định tại Khoản 6 Điều 7 <L rel="Reference"> Luật Điện_lực </L> ( hành_vi trộm_cắp điện ) , bên bán điện được ngừng cấp điện ngay sau khi Biên_bản vi_phạm hành_chính được lập theo quy_định tại <NĐ rel="Reference"> Nghị_định số 134/2013/NĐ-CP </NĐ> ngày 17 tháng 10 năm 2013 của Chính_phủ quy_định về xử_phạt vi_phạm hành_chính trong lĩnh_vực điện_lực , an_toàn đập thủy_điện , sử_dụng năng_lượng tiết_kiệm và hiệu_quả ( sau đây viết tắt là <NĐ rel="Reference"> Nghị_định số 134/2013/NĐ-CP </NĐ> ) ;
b ) Trường_hợp bên mua điện thực_hiện_hành_vi quy_định tại các Khoản 1 , 4 , 5 , 7 và Khoản 8 Điều 7 <L rel="Reference"> Luật Điện_lực </L> , nếu mức_độ vi_phạm chưa tới mức phải ngừng cấp điện khẩn_cấp thì sau khi Biên_bản vi_phạm hành_chính được lập theo quy_định tại <NĐ rel="Reference"> Nghị_định số 134/2013/NĐ-CP </NĐ> , bên bán điện có trách_nhiệm gửi thông_báo ngừng cấp điện cho bên mua điện trước thời_điểm ngừng cấp điện ít_nhất 24 giờ . Nếu quá thời_hạn này mà bên mua điện không chấm_dứt hành_vi vi_phạm và không tiến_hành khắc_phục hậu_quả do hành_vi vi_phạm gây ra theo yêu_cầu của bên bán điện thì bên bán điện có quyền ngừng cấp điện theo nội_dung đã thông_báo ;
c ) Trường_hợp bên mua điện vi_phạm_quy_định tại Điểm b Khoản 1 Điều 7 Thông_tư này , bên bán điện có quyền ngừng cấp điện cho bên mua điện và phải thông_báo cho bên mua điện trước thời_điểm ngừng cấp điện ít_nhất 24 giờ . 

2 . Đối_với trường_hợp quy_định tại Khoản 2 Điều 7 Thông_tư này 

a ) Trường_hợp không có thỏa_thuận lùi ngày thanh_toán tiền điện và bên mua điện đã được bên bán điện thông_báo về việc thanh_toán tiền điện 02 ( hai ) lần thì sau 15 ngày kể từ ngày thông_báo lần đầu_tiên , bên bán điện có quyền ngừng cấp điện cho bên mua điện ; 

b ) Trường_hợp bên mua điện có đề_nghị thỏa_thuận và được bên bán điện đồng_ý lùi ngày thanh_toán tiền điện , nếu quá thời_hạn thỏa_thuận lùi ngày thanh_toán tiền điện mà bên mua điện vẫn chưa thanh_toán đủ các khoản tiền còn nợ , bên bán điện có quyền ngừng cấp điện cho bên mua điện ; 

c ) Khi thực_hiện ngừng cấp điện , bên bán điện phải thông_báo cho bên mua điện trước thời_điểm ngừng cấp điện ít_nhất 24 giờ và không phải chịu trách_nhiệm về các thiệt_hại do việc ngừng cấp điện gây ra . 

3 . Đối_với trường_hợp quy_định tại Khoản 3 Điều 7 Thông_tư này 

Bên bán điện phải thông_báo ngừng cấp điện cho bên mua trước thời_điểm ngừng cấp điện ít_nhất 24 giờ và nêu rõ lý_do ngừng cấp điện .  Sau khi ngừng cấp điện , bên bán điện phải thông_báo bằng văn_bản về việc ngừng cấp điện cho cơ_quan nhà_nước có yêu_cầu ngừng cấp điện . 

4 . Đối_với trường_hợp quy_định tại Khoản 4 Điều 7 Thông_tư này 

Bên bán điện có quyền ngừng cấp điện cho bên mua điện theo thỏa_thuận trong hợp_đồng mua_bán điện và phải thông_báo cho bên mua điện trước thời_điểm ngừng cấp điện ít_nhất 24 giờ . 

5 . Việc cấp điện_trở_lại chỉ được tiến_hành trong các trường_hợp sau : 

a ) Bên mua điện đã thực_hiện đầy_đủ quyết_định xử_lý vi_phạm hành_chính của cơ_quan nhà_nước có thẩm_quyền , đã chấm_dứt hành_vi vi_phạm , đã tiến_hành khắc_phục hậu_quả do hành_vi vi_phạm gây ra và đã thanh_toán đầy_đủ chi_phí ngừng và cấp điện_trở_lại cho bên bán điện đối_với trường_hợp ngừng cấp điện theo quy_định tại Điểm a và Điểm b Khoản 1 Điều này ; 

b ) Thanh_toán đầy_đủ tiền nợ hoặc đã thực_hiện biện_pháp bảo_đảm thực_hiện các thỏa_thuận khác trong hợp_đồng mua_bán điện và chi_phí ngừng và cấp điện_trở_lại cho bên bán điện đối_với trường_hợp ngừng cấp điện theo quy_định tại Điểm_c Khoản 1 và Điểm a , Điểm b Khoản 2 Điều này ; 

c ) Có yêu_cầu cấp điện_trở_lại bằng văn_bản của cơ_quan có thẩm_quyền và bên mua điện đã thanh_toán đầy_đủ chi_phí ngừng và cấp điện_trở_lại cho bên bán điện đối_với trường_hợp ngừng cấp điện theo quy_định tại Khoản 3 Điều này ; 

d ) Bên mua điện đã thực_hiện biện_pháp bảo_đảm thực_hiện hợp_đồng hoặc duy_trì biện_pháp bảo_đảm thực_hiện hợp_đồng và đã thanh_toán đầy_đủ chi_phí ngừng và cấp điện_trở_lại cho bên bán điện đối_với trường_hợp ngừng cấp điện theo quy_định tại Khoản 4 Điều này . 

Điều 11 .  Báo_cáo định_kỳ hàng tháng 

1 . Trước ngày 15 hàng tháng , Tổng_công_ty Điện_lực thành_phố Hà_Nội , Tổng_công_ty Điện_lực thành_phố Hồ_Chí_Minh , Công_ty Điện_lực tỉnh , thành_phố trực_thuộc trung_ương và các Đơn_vị phân_phối và bán_lẻ điện được Cục Điều_tiết điện_lực cấp giấy_phép hoạt_động điện_lực có tổng quy_mô công_suất lắp_đặt của các trạm biến_áp từ 03 MVA trở lên có trách_nhiệm tổng_hợp , báo_cáo Sở Công_Thương tại địa_phương kết_quả thực_hiện ngừng , giảm mức cung_cấp điện tháng trước liền kề trong phạm_vi quản_lý .  Báo_cáo phải bao_gồm : 

a ) Báo_cáo tổng_hợp về tổng_số lần ngừng , giảm mức cung_cấp điện ;  tổng thời_gian ngừng , giảm mức cung_cấp điện ;  ước_tính tổng công_suất , điện_năng phụ_tải_điện và tổng_số khách_hàng bị ngừng , giảm cung_cấp của toàn đơn_vị theo quy_định tại Phụ_lục I ban_hành kèm Thông_tư này ; 

b ) Báo_cáo chi_tiết đối_với từng trường_hợp ngừng , giảm mức cung_cấp điện , gồm các nội_dung về tên trạm biến_áp hoặc đường_dây bị mất điện ;  thời_gian ngừng , giảm mức cung_cấp điện ;  nguyên_nhân ngừng , giảm mức cung_cấp điện ;  số_lượng khách_hàng bị ảnh_hưởng theo quy_định tại Phụ_lục II ban_hành kèm Thông_tư này .  Báo_cáo chi_tiết được gửi bằng văn_bản hoặc thư điện_tử ( Email ) . 

2 . Trước ngày 15 hàng tháng , các Tổng_công_ty Điện_lực có trách_nhiệm báo_cáo Cục Điều_tiết điện_lực về việc thực_hiện ngừng , giảm mức cung_cấp điện tháng trước liền kề trong phạm_vi quản_lý .  Báo_cáo bao_gồm các nội_dung quy_định tại Điểm a và Điểm b Khoản 1 Điều này . 

Điều 12 .  Báo_cáo đột_xuất 

1 . Khi xảy ra sự_cố nghiêm_trọng dẫn đến phải thực_hiện ngừng , giảm mức cung_cấp điện khẩn_cấp trên diện rộng trong hệ_thống điện quốc_gia , Tập_đoàn Điện_lực Việt_Nam có trách_nhiệm báo_cáo Bộ Công_Thương , Cục Điều_tiết điện_lực bằng thư điện_tử ( Email ) hoặc fax ngay sau khi xảy ra sự_cố và bằng văn_bản trong thời_hạn 24 giờ kể từ thời_điểm xảy ra sự_cố . 

2 . Khi phải thực_hiện ngừng , giảm mức cung_cấp điện khẩn_cấp trong trường_hợp sự_cố lưới_điện truyền_tải từ 220kV trở lên hoặc sự_cố các trạm biến_áp 110kV có vai_trò quan_trọng trong việc cung_cấp điện cho một khu_vực , Tập_đoàn Điện_lực Việt_Nam , Tổng_công_ty Điện_lực , Công_ty Điện_lực tỉnh có trách_nhiệm báo_cáo Cục Điều_tiết điện_lực và Sở Công_Thương các tỉnh bị ngừng , giảm cung_cấp điện bằng thư điện_tử ( Email ) hoặc fax ngay sau khi xảy ra sự_cố và bằng văn_bản trong thời_hạn 24 giờ kể từ thời_điểm xảy ra sự_cố . 

3 . Bên bán điện có trách_nhiệm báo_cáo việc thực_hiện ngừng , giảm mức cung_cấp điện khi có yêu_cầu của Cục Điều_tiết điện_lực hoặc Sở Công_Thương tại địa_phương . 

4 . Báo_cáo đột_xuất phải bao_gồm tối_thiểu các nội_dung quy_định tại Khoản 2 Điều 4 Thông_tư này . 

Điều 13 .  Giám_sát thực_hiện ngừng , giảm mức cung_cấp điện 

1 . Sở Công_Thương có trách_nhiệm : 

a ) Hàng năm , căn_cứ vào tầm quan_trọng về chính_trị , xã_hội , an_ninh và quốc_phòng , Sở Công_Thương chủ_trì và phối_hợp với Công_ty Điện_lực tại địa_phương để trình Ủy_ban nhân_dân cấp tỉnh phê_duyệt danh_sách khách_hàng sử_dụng điện quan_trọng thuộc diện ưu_tiên cấp điện khi bên bán điện thực_hiện ngừng , giảm mức cung_cấp điện trong hệ_thống điện . 

b ) Giám_sát việc thực_hiện ngừng , giảm mức cung_cấp điện của Tổng_công_ty Điện_lực , Công_ty Điện_lực , Đơn_vị phân_phối và bán_lẻ điện tại địa_phương theo quy_định tại Thông_tư này . 

2 . Cục Điều_tiết điện_lực có trách_nhiệm giám_sát chung việc thực_hiện ngừng , giảm mức cung_cấp điện của các đơn_vị điện_lực theo quy_định tại Thông_tư này . 

Điều 14 .  Tổ_chức thực_hiện 

1 . Cục Điều_tiết điện_lực có trách_nhiệm phổ_biến , hướng_dẫn và kiểm_tra việc thực_hiện Thông_tư này . 

2 . Tập_đoàn Điện_lực Việt_Nam có trách_nhiệm chỉ_đạo các đơn_vị trực_thuộc thực_hiện việc ngừng , giảm mức cung_cấp điện theo quy_định tại Thông_tư này . 

3 . Trong quá_trình thực_hiện Thông_tư này , nếu có vấn_đề vướng_mắc , nội_dung mới phát_sinh , các đơn_vị có liên_quan có trách_nhiệm báo_cáo Cục Điều_tiết điện_lực để nghiên_cứu , đề_xuất , trình Bộ Công_Thương sửa_đổi , bổ_sung Thông_tư cho phù_hợp . 

Điều 15 .  Hiệu_lực thi_hành 

1 . Thông_tư này có hiệu_lực thi_hành kể từ ngày 25 tháng 12 năm 2013 . <QĐ rel="Drop"> Quyết_định số 39/2005/QĐ-BCN ngày 23 tháng 12 năm 2005 </QĐ> của Bộ_trưởng Bộ_Công_nghiệp quy_định về điều_kiện , trình_tự và thủ_tục ngừng , giảm mức cung_cấp điện hết hiệu_lực thi_hành kể từ ngày Thông_tư này có hiệu_lực .
2 . Cục_trưởng Cục Điều_tiết điện_lực , Chánh_Văn_phòng Bộ , Chánh Thanh_tra Bộ , Tổng_Cục_trưởng Tổng_cục Năng_lượng , Vụ_trưởng các Vụ , Thủ_trưởng các đơn_vị có liên_quan thuộc Bộ Công_Thương và các tổ_chức , cá_nhân có liên_quan chịu trách_nhiệm thi_hành Thông_tư này ./. 
