Thông tư Quy định về quản lý tài chính đối với các chương trình, dự án sử dụng nguồn vốn hỗ trợ phát triển chính thức (ODA) và vay ưu đãi nước ngoài của các nhà tài trợ

Căn_cứ <L rel="Pursuant"> Luật Ngân_sách Nhà_nước số 01/2002/QH11 ngày 16/12/2002 </L> ;
Căn_cứ <L rel="Pursuant"> Luật Quản_lý nợ công số 29/2009/QH12 ngày 17/6/2009 </L> ;
Căn_cứ <NĐ rel="Pursuant"> Nghị_định số 60/2003/NĐ-CP ngày 6/6/2003 </NĐ> của Chính_phủ ban_hành quy_định chi_tiết và hướng_dẫn thi_hành <L rel="Others"> Luật Ngân_sách nhà_nước </L> ;
Căn_cứ <NĐ rel="Pursuant"> Nghị_định số 78/2010/NĐ-CP ngày 14/7/2010 </NĐ> của Chính_phủ về cho vay lại nguồn vốn vay nước_ngoài của Chính_phủ ;
Căn_cứ <NĐ rel="Pursuant"> Nghị_định số 79/2010/NĐ-CP ngày 14/7/2010 </NĐ> của Chính_phủ về nghiệp_vụ quản_lý nợ công ;
Căn_cứ <NĐ rel="Pursuant"> Nghị_định số 38/2013/NĐ-CP ngày 23/4/2013 </NĐ> của Chính_phủ về quản_lý và sử_dụng nguồn hỗ_trợ phát_triển chính_thức ( ODA ) và nguồn vốn vay ưu_đãi của các nhà tài_trợ ;
Căn_cứ <NĐ rel="Pursuant"> Nghị_định số 215/2013/NĐ-CP ngày 23/12/2013 </NĐ> của Chính_phủ quy_định chức_năng , nhiệm_vụ , quyền_hạn và cơ_cấu tổ_chức của Bộ Tài_chính ;
Căn_cứ vào quy_định về việc mở tài_khoản của chương_trình/dự_án theo khoản 1 Điều 10 Thông_tư này , đồng_thời theo yêu_cầu tổ_chức thực_hiện của chương_trình/dự_án và thỏa_thuận bằng văn_bản với nhà tài_trợ , chủ dự_án mở tài_khoản nguồn vốn ODA , vốn vay ưu_đãi của dự_án tại hệ_thống Kho_bạc nhà_nước để tiếp_nhận nguồn vốn ODA , vốn vay ưu_đãi tạm_ứng và thực_hiện thanh_toán cho dự_án sau khi có kiểm_soát chi của Kho_bạc nhà_nước . 

Điều 1 .  Phạm_vi điều_chỉnh 

1 . Thông_tư này hướng_dẫn chế_độ quản_lý_tài_chính đối_với các chương_trình , dự_án sử_dụng nguồn vốn hỗ_trợ phát_triển chính_thức ( vốn ODA ) và vay ưu_đãi nước_ngoài của các nhà tài_trợ quy_định tại <NĐ rel="Reference"> Nghị_định số 38/2013/NĐ-CP ngày 23/4/2013 </NĐ> của Chính_phủ về quản_lý và sử_dụng nguồn hỗ_trợ phát_triển chính_thức ( ODA ) và nguồn vốn vay ưu_đãi của các nhà tài_trợ .
2 . Đối_với các chương_trình , dự_án có đặc_thù riêng sử_dụng vốn vay ODA và vốn vay ưu_đãi , tùy theo yêu_cầu quản_lý , Bộ Tài_chính hoặc liên Bộ Tài_chính , Bộ chủ_quản sẽ ban_hành hướng_dẫn chế_độ quản_lý_tài_chính cho từng chương_trình , dự_án cụ_thể . 

3 . Các khoản ODA viện_trợ không hoàn lại được giải_ngân riêng cho các dự_án/dự_án thành_phần độc_lập thuộc một chương_trình , dự_án sử_dụng vốn ODA vay và vốn vay ưu_đãi , được điều_chỉnh theo quy_định tại <TT rel="Reference"> Thông_tư số 225/2010/TT-BTC ngày 31/12/2010 </TT> của Bộ Tài_chính hướng_dẫn chế_độ quản_lý_tài_chính nhà_nước đối_với viện_trợ không hoàn lại nước_ngoài thuộc nguồn thu ngân_sách nhà_nước và các văn_bản sửa_đổi , bổ_sung hoặc thay_thế Thông_tư trên , không thuộc phạm_vi điều_chỉnh của Thông_tư này .
4 . Các khoản vay nước_ngoài được Chính_phủ bảo_lãnh , được điều_chỉnh theo các quy_định tại <NĐ rel="Reference"> Nghị_định số 15/2011/NĐ-CP ngày 16/02/2011 </NĐ> của Chính_phủ về cấp và quản_lý bảo_lãnh của Chính_phủ và các văn_bản hướng_dẫn Nghị_định này , không thuộc phạm_vi điều_chỉnh của Thông_tư này .
5 . Trong trường_hợp các quy_định về quản_lý_tài_chính tại Thông_tư này có sự khác_biệt với các Điều_ước quốc_tế về ODA và vốn vay ưu_đãi thì áp_dụng theo các quy_định của Điều_ước quốc_tế đó . 

6 . Các từ_ngữ sử_dụng trong Thông_tư này được hiểu thống_nhất với Điều 3 , Điều 4 <NĐ rel="Reference"> Nghị_định số 38/2013/NĐ-CP ngày 23/4/2013 </NĐ> của Chính_phủ .
Điều 2 .  Đối_tượng áp_dụng 

Đối_tượng áp_dụng Thông_tư này là các cơ_quan , tổ_chức , cá_nhân được giao trách_nhiệm hoặc có liên_quan đến việc quản_lý , sử_dụng vốn ODA và vốn vay ưu_đãi nước_ngoài của các nhà tài_trợ . 

Điều 3 .  Cơ_chế_tài_chính trong nước áp_dụng đối_với các chương_trình , dự_án sử_dụng vốn ODA và vốn vay ưu_đãi nước_ngoài 

1 . Nguyên_tắc xác_định cơ_chế_tài_chính ( cấp_phát , cho vay lại ) 

a ) Cấp_phát từ ngân_sách nhà_nước từ nguồn vốn ODA và vay ưu_đãi nước_ngoài cho chương_trình , dự_án đầu_tư cơ_sở hạ_tầng , phúc_lợi xã_hội và chương_trình , dự_án thuộc các lĩnh_vực khác không có khả_năng thu_hồi vốn trực_tiếp thuộc nhiệm_vụ chi của ngân_sách nhà_nước , theo quy_định của <L rel="Reference"> Luật Ngân_sách nhà_nước </L> .
b ) Cho vay lại toàn_bộ hoặc một phần từ nguồn vốn ODA và vay ưu_đãi nước_ngoài đối_với : 

- Các chương_trình , dự_án đầu_tư có khả_năng thu_hồi toàn_bộ hoặc một phần vốn ODA và vay ưu_đãi , bao_gồm cả dự_án xây_dựng cơ_sở hạ_tầng , phù_hợp với định_hướng phát_triển kinh_tế-xã_hội của đất_nước đã được cấp có thẩm_quyền phê_duyệt ; 

- Các chương_trình , dự_án không thuộc nhiệm_vụ chi của ngân_sách nhà_nước ; 

- Các chương_trình , dự_án do Ủy_ban nhân_dân cấp tỉnh là cơ_quan chủ_quản thuộc đối_tượng phải vay lại vốn vay ODA và vốn vay ưu_đãi của Chính_phủ . 

c ) Đối_với các chương_trình , dự_án có cơ_chế giải_ngân và thu_hồi vốn đặc_biệt , đòi_hỏi phải áp_dụng cơ_chế_tài_chính đặc_thù ( dự_án giải_ngân dựa trên kết_quả , giải_ngân theo mốc tiến_độ dự_án , dự_án PPP , dự_án hỗn_hợp nhiều nguồn vốn tài_trợ khác nhau ) , Bộ Tài_chính chủ_trì , phối_hợp với Bộ Kế_hoạch và Đầu_tư , cơ_quan chủ_quản và chủ dự_án nghiên_cứu , báo_cáo Thủ_tướng Chính_phủ xem_xét và quyết_định cơ_chế_tài_chính riêng áp_dụng cho từng chương_trình , dự_án . 

d ) Trường_hợp trong dự_thảo Điều_ước quốc_tế về vốn ODA và vốn vay ưu_đãi với các nhà tài_trợ có các quy_định khác về cơ_chế_tài_chính áp_dụng đối_với chương_trình , dự_án , Bộ Tài_chính phối_hợp với Bộ Kế_hoạch và Đầu_tư và cơ_quan chủ_trì đàm_phán báo_cáo Thủ_tướng Chính_phủ xem_xét và quyết_định . 

2 . Tính_chất sử_dụng vốn của dự_án được xác_định theo các loại_hình dự_án sau : 

a ) Dự_án xây_dựng cơ_bản ( sau đây viết tắt là " XDCB " ) : là dự_án đầu_tư liên_quan đến việc xây_dựng mới , mở_rộng hoặc cải_tạo những công_trình xây_dựng nhằm mục_đích duy_tu , phát_triển , nâng cao chất_lượng công_trình ; 

b ) Dự_án hành_chính sự_nghiệp ( sau đây viết tắt là " HCSN " ) : là dự_án đầu_tư cho các nội_dung chỉ có tính_chất HCSN , không thuộc nội_dung của dự_án đầu_tư quy_định tại tiết a ) khoản này ; 

c ) Dự_án cho vay lại : là dự_án đầu_tư từ nguồn vốn vay lại nguồn vốn vay nước_ngoài của Chính_phủ ; 

d ) Dự_án hỗn_hợp : là dự_án kết_hợp ít_nhất hai trong ba nội_dung chi có tính_chất XDCB , HCSN hay dự_án cho vay lại ( gồm cả cho vay lại theo các chương_trình , hạn_mức tín_dụng ) . 

Đối_với dự_án hỗn_hợp , chủ dự_án cần xác_định rõ các thành_phần hay nội_dung chi của dự_án thuộc nguồn vốn XDCB và thuộc nguồn vốn HCSN .  Trường_hợp đặc_biệt , nếu nội_dung chi của dự_án có tính hỗn_hợp nhưng chủ dự_án đề_xuất được áp_dụng theo cùng một tính_chất chi sử_dụng vốn là XDCB hoặc HCSN , chủ dự_án phải giải_trình rõ đề_xuất của mình với cơ_quan chủ_quản trong quá_trình chuẩn_bị và trình_duyệt dự_án để cơ_quan có thẩm_quyền xem_xét , quyết_định . 

3 . Quy_trình xác_định cơ_chế_tài_chính trong nước 

a ) Cơ_quan chủ_quản và chủ dự_án phối_hợp với nhà tài_trợ xây_dựng Đề_cương chương_trình , dự_án , theo mẫu Đề_cương chương_trình , dự_án quy_định tại Điều 16 <NĐ rel="Reference"> Nghị_định số 38/2013/NĐ-CP ngày 23/4/2013 </NĐ> của Chính_phủ về quản_lý và sử_dụng nguồn hỗ_trợ phát_triển chính_thức ( ODA ) và nguồn vốn vay ưu_đãi .
- Đề_cương chương_trình , dự_án phải bao_gồm nội_dung về tổng mức vốn ODA , vay ưu_đãi và vốn đối_ứng_đối_với chương_trình dự_án , kèm theo đề_xuất cơ_chế_tài_chính trong nước áp_dụng đối_với vốn ODA và vốn vay ưu_đãi , nêu rõ khả_năng và phương_án trả nợ ( đối_với các chương_trình , dự_án vay lại ) , được xác_định theo các nguyên_tắc quy_định ở khoản 1 Điều này . 

- Bộ Tài_chính có ý_kiến về nguyên_tắc đối_với kiến_nghị về cơ_chế_tài_chính trong nước nêu tại Đề_cương của chương_trình , dự_án sử_dụng vốn vay ODA và vốn vay ưu_đãi .  Bộ Kế_hoạch và Đầu_tư tổng_hợp và trình Thủ_tướng Chính_phủ phê_duyệt Danh_mục tài_trợ ( đối_với Danh_mục tài_trợ thuộc thẩm_quyền phê_duyệt của Thủ_tướng Chính_phủ ) . 

- Bộ Kế_hoạch và Đầu_tư có ý_kiến về nguyên_tắc cơ_chế_tài_chính trong nước nêu tại Đề_cương của chương_trình , dự_án sử_dụng vốn ODA viện_trợ không hoàn lại .  Cơ_quan chủ_quản xem_xét quyết_định phê_duyệt Danh_mục tài_trợ ( đối_với Danh_mục tài_trợ thuộc thẩm_quyền phê_duyệt của cơ_quan chủ_quản ) . 

b ) Trường_hợp trong giai_đoạn xây_dựng và phê_duyệt Danh_mục tài_trợ nêu tại điểm a ) trên , nêu chưa có đủ cơ_sở và thông_tin chi_tiết để đề_xuất cơ_chế_tài_chính cụ_thể đối_với dự_án , cơ_quan chủ_quản và chủ dự_án phải tiếp_tục nghiên_cứu và đề_xuất cơ_chế_tài_chính trong nước áp_dụng đối_với dự_án gửi Bộ Tài_chính và các cơ_quan liên_quan tham_gia ý_kiến trước khi trình cấp có thẩm_quyền phê_duyệt Văn_kiện chương_trình , dự_án/Báo_cáo nghiên_cứu_khả_thi dự_án đầu_tư . 

c ) Trường_hợp trong quá_trình đàm_phán Hiệp_định vay/Thỏa_thuận tài_trợ phát_sinh các nội_dung mới chưa được xác_định cơ_chế_tài_chính trong giai_đoạn phê_duyệt Văn_kiện chương_trình , dự_án/Báo_cáo nghiên_cứu_khả_thi dự_án đầu_tư , hoặc phát_sinh các yếu_tố khách_quan khác đòi_hỏi phải bổ_sung , sửa_đổi cơ_chế_tài_chính trong Văn_kiện chương_trình , dự_án/Báo_cáo nghiên_cứu_khả_thi dự_án đầu_tư được duyệt , cơ_quan chủ_quản và chủ dự_án có trách_nhiệm báo_cáo Bộ Tài_chính để xem_xét và trình Thủ_tướng Chính_phủ phê_duyệt cơ_chế_tài_chính trong nước áp_dụng chính_thức đối_với chương_trình , dự_án sử_dụng nguồn vốn vay ODA và vốn vay ưu_đãi , trước khi Hiệp_định vay/Thỏa_thuận tài_trợ được ký_kết . 

4 . Xác_định điều_khoản và điều_kiện cho vay lại cụ_thể đối_với các chương_trình , dự_án sử_dụng vốn ODA và vốn vay ưu_đãi nước_ngoài : 

a ) Căn_cứ vào kết_quả thẩm_định phương_án tài_chính của chương_trình , dự_án cho vay lại và kết_quả thẩm_định về năng_lực tài_chính của chủ dự_án của Cơ_quan cho vay lại , Bộ Tài_chính áp_dụng các điều_khoản và điều_kiện cho vay lại quy_định tại <NĐ rel="Reference"> Nghị_định số 78/2010/NĐ-CP ngày 14/7/2010 </NĐ> của Chính_phủ đối_với các chương_trình , dự_án cho vay lại và các quy_định cụ_thể tại Thông_tư này .
Thời_gian thẩm_định và thông_báo điều_kiện cho vay lại thực_hiện theo quy_định cụ_thể tại Điều 19 <NĐ rel="Reference"> Nghị_định số 78/2010/NĐ-CP ngày 14/7/2010 </NĐ> của Chính_phủ .
b ) Trong các trường_hợp đặc_biệt , kể_cả trường_hợp bên cho vay nước_ngoài yêu_cầu áp_dụng các điều_khoản và điều_kiện cho vay lại khác với quy_định của <NĐ rel="Reference"> Nghị_định số 78/2010/NĐ-CP ngày 14/7/2010 </NĐ> của Chính_phủ , Bộ Tài_chính chủ_trì nghiên_cứu , xin ý_kiến của các cơ_quan liên_quan để báo_cáo Thủ_tướng Chính_phủ xem_xét và quyết_định từng trường_hợp cụ_thể .
5 . Bộ Tài_chính hoặc Cơ_quan cho vay lại được Bộ Tài_chính ủy_quyền ký_kết các Thỏa_thuận cho vay lại/Hiệp_định vay phụ với Người vay lại , căn_cứ vào các điều_khoản và điều_kiện cho vay lại cụ_thể được xác_định theo quy_định tại khoản 3 và 4 Điều này để làm căn_cứ quản_lý việc sử_dụng và thu_hồi vốn vay lại . 

Điều 4 .  Cơ_chế_tài_chính trong nước áp_dụng đối_với chương_trình , dự_án của các địa_phương 

1 . Cấp_phát nguồn vốn ODA và vốn vay ưu_đãi nước_ngoài cho các địa_phương 

Ngân_sách Trung_ương cấp_phát theo hình_thức hỗ_trợ có mục_tiêu cho ngân_sách địa_phương từ nguồn vốn ODA và vốn vay ưu_đãi nước_ngoài của Chính_phủ , để thực_hiện các dự_án đầu_tư cơ_sở hạ_tầng , phúc_lợi xã_hội và các dự_án thuộc lĩnh_vực khác không có khả_năng thu_hồi vốn trực_tiếp và thuộc nhiệm_vụ chi của ngân_sách nhà_nước theo quy_định của <L rel="Reference"> Luật Ngân_sách nhà_nước </L> .
2 . Cho vay lại toàn_bộ hoặc một phần nguồn vốn ODA của Chính_phủ đối_với : 

a ) Dự_án đầu_tư phát_triển kinh_tế-xã_hội thuộc nhiệm_vụ chi của ngân_sách địa_phương đã hoàn_thành thủ_tục đầu_tư và ngân_sách địa_phương bảo_đảm trả được nợ . 

b ) Các dự_án thành_phần trên địa_bàn tỉnh , thành_phố , thuộc các chương_trình dự_án ô do các Bộ là cơ_quan chủ_quản và chủ chương_trình dự_án , có khả_năng thu_hồi vốn và do các chủ dự_án thành_phần thuộc Ủy_ban nhân_dân cấp tỉnh thực_hiện . 

3 . Căn_cứ vào mục_đích sử_dụng của từng khoản vay , Bộ Tài_chính trình Thủ_tướng Chính_phủ quyết_định cơ_chế cho vay lại cụ_thể đối_với từng dự_án . 

4 . Ủy_ban nhân_dân cấp tỉnh được vay lại vốn ODA và vốn vay ưu_đãi nước_ngoài khi đáp_ứng đầy_đủ các điều_kiện sau : 

a ) Được cấp có thẩm_quyền cho phép vay lại từ nguồn vốn vay nước_ngoài của Chính_phủ ; 

b ) Có dự_án đầu_tư phát_triển kinh_tế-xã_hội thuộc nhiệm_vụ chi của ngân_sách địa_phương đã hoàn_thành thủ_tục đầu_tư theo quy_định của pháp_luật về đầu_tư và các quy_định của pháp_luật có liên_quan ; 

c ) Ngân_sách địa_phương được đánh_giá là có khả_năng trả được nợ . 

5 . Bộ Tài_chính thẩm_định khả_năng trả nợ của ngân_sách cấp tỉnh theo quy_định của <NĐ rel="Reference"> Nghị_định số 78/2010/NĐ-CP ngày 14/7/2010 </NĐ> của Chính_phủ và các quy_định pháp_luật có liên_quan và trình Thủ_tướng Chính_phủ quyết_định cơ_chế_tài_chính trong nước áp_dụng cho từng nguồn vốn ODA và vốn vay ưu_đãi của địa_phương .
Điều 5 .  Điều_kiện cho vay lại áp_dụng đối_với các tổ_chức tài_chính , tín_dụng vay lại theo chương_trình , hạn_mức tín_dụng 

1 . Điều_kiện được vay lại đối_với các tổ_chức tài_chính , tín_dụng : 

a ) Có chương_trình , dự_án được cấp có thẩm_quyền cho phép sử_dụng vốn vay và được bên cho vay nước_ngoài chấp_thuận ; 

b ) Bảo_đảm khả_năng trả nợ theo phương_án tài_chính được thẩm_định theo quy_định của pháp_luật . 

2 . Điều_kiện cho vay lại từ Bộ Tài_chính đến các tổ_chức tài_chính , tín_dụng tham_gia chương_trình , hạn_mức tín_dụng : 

a ) Lãi_suất cho vay lại thực_hiện theo quy_định tại <NĐ rel="Reference"> Nghị_định số 78/2010/NĐ-CP ngày 14/7/2010 </NĐ> của Chính_phủ .
b ) Thời_hạn vay , ân hạn áp_dụng đối_với tổ_chức tài_chính , tín_dụng tối_đa không quá thời_hạn vay , ân hạn khoản vay gốc của nước_ngoài . 

c ) Trong các trường_hợp đặc_biệt , kể_cả trường_hợp bên cho vay nước_ngoài yêu_cầu áp_dụng các điều_kiện cho vay lại khác với quy_định của <NĐ rel="Reference"> Nghị_định số 78/2010/NĐ-CP ngày 14/7/2010 </NĐ> của Chính_phủ , Bộ Tài_chính chủ_trì nghiên_cứu , xin ý_kiến của các cơ_quan liên_quan để báo_cáo Thủ_tướng Chính_phủ xem_xét và quyết_định từng trường_hợp cụ_thể .
3 . Thẩm_định và lựa_chọn tổ_chức tài_chính , tín_dụng tham_gia chương_trình , hạn_mức tín_dụng 

a ) Trường_hợp cho vay lại vốn vay ODA : Bộ Tài_chính_trực_tiếp thẩm_định phương_án sử_dụng vốn vay và trả nợ của các tổ_chức tài_chính , tín_dụng tham_gia chương_trình trước khi ký_kết Thỏa_thuận cho vay lại/Hiệp_định vay phụ . 

b ) Trường_hợp cho vay lại vốn vay ưu_đãi : Ngân_hàng Nhà_nước Việt_Nam thẩm_định năng_lực tài_chính và phương_án sử_dụng vốn vay và trả nợ của tổ_chức tài_chính , tín_dụng tham_gia chương_trình , hạn_mức tín_dụng và thông_báo cho Bộ Tài_chính kết_quả thẩm_định trước khi ký_kết Thỏa_thuận cho vay lại/Hiệp_định vay phụ . 

c ) Tổ_chức tài_chính , tín_dụng cho vay đến người sử_dụng vốn cuối_cùng chịu trách_nhiệm thẩm_định dự_án và chọn người vay lại cuối_cùng phù_hợp với chương_trình tín_dụng đã thỏa_thuận với nhà tài_trợ , đồng_thời chịu mọi rủi_ro phát_sinh từ việc cho vay lại . 

Điều 6 .  Cơ_chế_tài_chính trong nước áp_dụng đối_với khu_vực tư_nhân khi tiếp_cận nguồn vốn ODA , vốn vay ưu_đãi nước_ngoài 

1 . Khu_vực tư_nhân được tiếp_cận vốn ODA và vốn vay ưu_đãi nước_ngoài thông_qua cơ_chế cho vay lại , cụ_thể như sau : 

a ) Được vay lại vốn ODA và vốn vay ưu_đãi khi tham_gia thực_hiện các dự_án đầu_tư thuộc các lĩnh_vực ưu_tiên sử_dụng vốn ODA và vốn vay ưu_đãi của Chính_phủ theo cơ_chế_tài_chính trong nước quy_định tại Điều 3 Thông_tư này . 

b ) Được vay lại vốn ODA và vốn vay ưu_đãi từ các tổ_chức tài_chính , tín_dụng trong nước thông_qua các chương_trình , hạn_mức tín_dụng và được áp_dụng cơ_chế_tài_chính trong nước quy_định tại Điều 5 Thông_tư này . 

c ) Được vay lại vốn vay ưu_đãi của Chính_phủ theo đúng các điều_kiện Chính_phủ vay của nước_ngoài , khi tham_gia thực_hiện các dự_án đầu_tư theo hình_thức đối_tác công_tư ( PPP ) . 

d ) Tham_gia thực_hiện các chương_trình , dự_án có mục_tiêu hỗ_trợ khu_vực kinh_tế tư_nhân của cơ_quan chủ_quản chương_trình : Cơ_quan chủ_quản chương_trình có trách_nhiệm thẩm_định các dự_án của khu_vực kinh_tế tư_nhân tham_gia chương_trình , dự_án trên cơ_sở cơ_chế_tài_chính chung đã được cấp có thẩm_quyền phê_duyệt . 

Trường_hợp chưa có cơ_chế_tài_chính chung của chương_trình , dự_án được duyệt , cơ_quan chủ_quản đề_xuất cơ_chế_tài_chính trong nước áp_dụng đối_với từng chương_trình , dự_án gửi Bộ Tài_chính để xem_xét và trình Thủ_tướng Chính_phủ quyết_định . 

2 . Điều_kiện được xem_xét để tiếp_cận vốn ODA , vay ưu_đãi và yêu_cầu thẩm_định đối_với chủ dự_án : 

a ) Điều_kiện được xem_xét để tiếp_cận vốn ODA , vốn vay ưu_đãi đối_với chủ dự_án là doanh_nghiệp thuộc khu_vực kinh_tế tư_nhân 

- Trường_hợp thực_hiện các dự_án đầu_tư phải bảo_đảm tối_thiểu 20 % tổng mức vốn đầu_tư được cấp thẩm_quyền phê_duyệt là vốn chủ sở_hữu ( sau khi trừ đi phần vốn chủ sở_hữu thực_hiện dự_án đầu_tư khác-nếu có dự_án khác đang triển_khai ) .  Chủ dự_án phải báo_cáo cho cơ_quan , tổ_chức thẩm_định danh_mục dự_án đang đầu_tư , trong đó nêu rõ số vốn đầu_tư , tiến_độ đầu_tư , phương_án sử_dụng vốn chủ sở_hữu và vốn huy_động để thực_hiện các dự_án đó , làm cơ_sở xem_xét điều_kiện tiếp_cận vốn ODA , vốn vay ưu_đãi và chịu trách_nhiệm về tính chính_xác của báo_cáo . 

- Tình_hình tài_chính lành_mạnh , không bị lỗ trong 3 năm liền kề gần nhất với năm đề_xuất tiếp_cận vốn ODA và vốn vay ưu_đãi , không có lỗ lũy_kế và đảm_bảo ngưỡng an_toàn về hệ_số nợ , hệ_số thanh_toán ;  tại thời_điểm đề_xuất tiếp_nhận vốn ODA và vốn vay ưu_đãi không có nợ quá hạn với các tổ_chức tài_chính , tín_dụng ;  không có nợ quá hạn liên_quan đến khoản được Chính_phủ bảo_lãnh , các khoản vay lại vốn vay nước_ngoài của Chính_phủ và ngân_sách nhà_nước .  Nếu doanh_nghiệp chưa đủ 3 năm hoạt_động liên_tục thì phải có văn_bản của chủ sở_hữu hoặc của công_ty_mẹ về cam_kết trả nợ thay cho doanh_nghiệp , trong trường_hợp_doanh_nghiệp không trả được nợ vay lại của Chính_phủ .  Trường_hợp không có công_ty_mẹ hay chủ sở_hữu , doanh_nghiệp phải có bảo_lãnh trách_nhiệm trả nợ của một ngân_hàng thương_mại hoặc một hình_thức bảo_đảm khác được Bộ Tài_chính chấp_thuận . 

- Doanh_nghiệp vay lại phải sử_dụng các biện_pháp bảo_đảm tiền vay theo quy_định của pháp_luật để đảm_bảo bù_đắp rủi_ro tín_dụng và các rủi_ro khác có_thể xảy ra .  Tài_sản đảm_bảo bao_gồm tài_sản hình_thành từ vốn vay của Chính_phủ và các tài_sản khác theo quy_định của pháp_luật . 

b ) Thẩm_định và lựa_chọn các chủ dự_án là doanh_nghiệp thuộc khu_vực kinh_tế tư_nhân : 

- Đối_với các chương_trình , hạn_mức tín_dụng : tổ_chức tài_chính-tín_dụng thẩm_định và lựa_chọn theo quy_định tại điểm c ) khoản 3 Điều 5 trên . 

- Đối_với các dự_án đầu_tư thuộc các lĩnh_vực ưu_tiên sử_dụng vốn ODA và vốn vay ưu_đãi của Chính_phủ nêu tại điểm c ) khoản 1 Điều này .  Sau khi dự_án đầu_tư đã hoàn_thành thủ_tục đầu_tư theo quy_định của pháp_luật về đầu_tư và được cấp có thẩm_quyền thẩm_định và quyết_định đầu_tư , Bộ Tài_chính có_thể ủy_quyền cho cơ_quan cho vay lại hoặc thuê tổ_chức tư_vấn độc_lập để thẩm_định về năng_lực tài_chính và phương_án trả nợ của chủ dự_án .  Tổ_chức thẩm_định chịu trách_nhiệm về kết_quả thẩm_định .  Chủ dự_án chịu trách_nhiệm thanh_toán chi_phí thẩm_định và được tính vào tổng vốn đầu_tư của dự_án ( trường_hợp được tiếp_nhận vốn ODA và vốn vay ưu_đãi ) hoặc tính vào chi_phí sản_xuất kinh_doanh của doanh_nghiệp chủ dự_án . 

c ) Điều_kiện tiếp_nhận vốn ODA và vốn vay ưu_đãi đối_với khu_vực kinh_tế tư_nhân trong các chương_trình , hạn_mức tín_dụng , trong trường_hợp chủ dự_án là thể_nhân như các hộ kinh_doanh , cá_nhân , sẽ do tổ_chức tài_chính tín_dụng thẩm_định và quy_định cho từng trường_hợp cụ_thể . 

Điều 7 .  Xây_dựng kế_hoạch vốn hàng năm 

1 . Kế_hoạch vốn hàng năm của các chương_trình , dự_án sử_dụng vốn ODA và vốn vay ưu_đãi là kế_hoạch giải_ngân ODA , vốn vay ưu_đãi và kế_hoạch vốn đối_ứng nêu tại các Điều 61 và 62 <NĐ rel="Reference"> Nghị_định số 38/2013/NĐ-CP ngày 23/4/2013 </NĐ> của Chính_phủ . Mẫu biểu kế_hoạch giải_ngân vốn ODA và vốn vay ưu_đãi và kế_hoạch vốn đối_ứng được thực_hiện thống_nhất theo <TT rel="Reference"> Thông_tư của Bộ Kế_hoạch và Đầu_tư hướng_dẫn thi_hành <NĐ rel="Others"> Nghị_định số 38/2013/NĐ-CP ngày 23/4/2013 </NĐ> </TT> của Chính_phủ .
2 . Căn_cứ vào kế_hoạch tổng_thể thực_hiện chương_trình , dự_án được cơ_quan chủ_quản phê_duyệt , quy_định tại Điều 37 <NĐ rel="Reference"> Nghị_định số 38/2013/NĐ-CP ngày 23/4/2013 </NĐ> của Chính_phủ , chủ dự_án lập kế_hoạch thực_hiện chương_trình , dự_án hàng năm để làm cơ_sở phê_duyệt kế_hoạch phân_bổ vốn hàng năm của cơ_quan chủ_quản , quy_định tại Điều 38 <NĐ rel="Reference"> Nghị_định số 38/2013/NĐ-CP ngày 23/4/2013 </NĐ> của Chính_phủ , bao_gồm :
a ) Kế_hoạch giải_ngân vốn ODA và vốn vay ưu_đãi hàng năm được lập theo từng nhà tài_trợ và được phân_bổ theo tính_chất sử_dụng vốn ( xây_dựng cơ_bản , hành_chính sự_nghiệp , cho vay lại , hỗ_trợ ngân_sách ) . 

b ) Kế_hoạch giải_ngân vốn đối_ứng hàng năm được lập theo từng cơ_quan chủ_quản và được phân_bổ theo nguồn bố_trí vốn ( ngân_sách trung_ương , ngân_sách địa_phương , vốn chủ dự_án và nguồn vốn khác ) 

Các nội_dung kế_hoạch vốn đối_ứng để chuẩn_bị thực_hiện và thực_hiện chương_trình , dự_án sử_dụng vốn ODA và vốn vay ưu_đãi , được quy_định cụ_thể tại Điều 43 <NĐ rel="Reference"> Nghị_định số 38/2013/NĐ-CP ngày 23/4/2013 </NĐ> của Chính_phủ . Các cơ_quan chủ_quản phải ưu_tiên bố_trí vốn đối_ứng trong dự_toán ngân_sách hàng năm nhằm thực_hiện các cam_kết tại các điều_ước quốc_tế về ODA và vay ưu_đãi và phù_hợp với khả_năng giải_ngân thực_tế hàng năm của các chương_trình , dự_án sử_dụng vốn ODA và vốn vay ưu_đãi .
3 . Cơ_quan chủ_quản có trách_nhiệm tổng_hợp và phê_duyệt kế_hoạch phân_bổ vốn hàng năm của chương_trình , dự_án , theo quy_định tại Điều 37 <NĐ rel="Reference"> Nghị_định số 38/2013/NĐ-CP ngày 23/4/2013 </NĐ> của Chính_phủ , gửi cho Bộ Kế_hoạch và Đầu_tư , Bộ Tài_chính và các cơ_quan liên_quan khác ( cơ_quan kiểm_soát chi , cơ_quan cho vay lại , ngân_hàng_phục_vụ ) .
4 . Đối_với các dự_án thuộc diện ngân_sách nhà_nước cấp_phát , Bộ Kế_hoạch và Đầu_tư lập và tổng_hợp kế_hoạch giải_ngân vốn ODA và vốn vay ưu_đãi , kế_hoạch vốn đối_ứng hàng năm , quy_định tại Điều 61 <NĐ rel="Reference"> Nghị_định số 38/2013/NĐ-CP ngày 23/4/2013 </NĐ> của Chính_phủ , gửi Bộ Tài_chính để tổng_hợp vào kế_hoạch ngân_sách nhà_nước_hàng năm .
5 . Đối_với các dự_án vay lại vốn ODA và vốn vay ưu_đãi của Chính_phủ và vốn đối_ứng do chủ dự_án tự bố_trí , chủ dự_án tự chịu trách_nhiệm về lập và phê_duyệt kế_hoạch vốn hàng năm . 

Điều 8 .  Quy_trình lập kế_hoạch vốn hàng năm 

1 . Đối_với các dự_án thuộc diện ngân_sách cấp_phát : 

a ) Hàng năm , vào thời_điểm lập , trình và xét_duyệt dự_toán ngân_sách nhà_nước theo quy_định hiện_hành , chủ dự_án căn_cứ tiến_độ thực_hiện dự_án lập kế_hoạch vốn đầu_tư của dự_án hay kế_hoạch vốn sự_nghiệp gửi cơ_quan chủ_quản để tổng_hợp vào kế_hoạch ngân_sách chung gửi Bộ Tài_chính , Bộ Kế_hoạch và Đầu_tư để trình Thủ_tướng Chính_phủ và Quốc_hội phê_duyệt . 

b ) Quy_trình phê_duyệt , phân_bổ và thông_báo kế_hoạch vốn tuân_thủ đúng các quy_định hiện_hành về lập và chấp_hành ngân_sách nhà_nước .  Quyết_định phê_duyệt của cơ_quan chủ_quản về kế_hoạch phân_bổ hàng năm phải được gửi đến cơ_quan_tài_chính đồng cấp và cơ_quan kiểm_soát chi . 

c ) Trường_hợp điều_ước quốc_tế về dự_án đã ký_kết nhưng chưa có hiệu_lực , hoặc đã có hiệu_lực nhưng dự_án chưa hoàn_thành các thủ_tục đầu_tư trong nước , trong thời_hạn lập dự_toán ngân_sách hàng năm , cơ_quan chủ_quản có trách_nhiệm báo_cáo Bộ Kế_hoạch và Đầu_tư và Bộ Tài_chính về nhu_cầu vốn đối_ứng , vốn ứng trước của dự_án để kịp_thời bố_trí hoặc trình cấp có thẩm_quyền quyết_định ( trong trường_hợp ngân_sách trung_ương chịu trách_nhiệm bố_trí vốn đối_ứng ) ;  hoặc chủ dự_án có trách_nhiệm báo_cáo cơ_quan chủ_quản dự_án ở địa_phương về nhu_cầu vốn đối_ứng , vốn ứng trước của dự_án trình cấp có thẩm_quyền để kịp_thời bố_trí hoặc trình cấp có thẩm_quyền quyết_định ( trong trường_hợp ngân_sách địa_phương chịu trách_nhiệm bố_trí vốn đối_ứng ) . 

d ) Đối_với các dự_án phát_sinh sau thời_điểm lập dự_toán ngân_sách hàng năm , cơ_quan chủ_quản dự_án lập kế_hoạch tài_chính bổ_sung hoặc ứng trước dự_toán ngân_sách năm sau gửi cơ_quan_tài_chính , cơ_quan kế_hoạch và đầu_tư xử_lý theo quy_định của <L rel="Reference"> Luật Ngân_sách Nhà_nước </L> và các văn_bản hướng_dẫn hiện_hành .
2 . Đối_với các dự_án cho vay lại 

Hàng năm , cùng thời_điểm lập dự_toán ngân_sách nhà_nước theo quy_định hiện_hành , chủ dự_án lập kế_hoạch vốn hàng năm của dự_án , trong đó nêu rõ nguồn vốn ODA , vốn vay ưu_đãi và vốn đối_ứng , gửi Bộ Tài_chính và Bộ Kế_hoạch và Đầu_tư .  Chủ dự_án có trách_nhiệm tự cân_đối đủ vốn đối_ứng theo tiến_độ thực_hiện dự_án . 

3 . Đối_với các dự_án hỗn_hợp vừa cấp_phát , vừa cho vay lại 

Tùy theo cơ_chế_tài_chính áp_dụng đối_với từng hợp_phần dự_án là cấp_phát hay cho vay lại , chủ dự_án áp_dụng quy_trình lập và trình_duyệt kế_hoạch phân_bổ vốn của dự_án tương_ứng với từng hợp_phần , theo quy_định tại các khoản 1 và 2 Điều này . 

Điều 9 .  Lựa_chọn ngân_hàng_phục_vụ 

1 . " Ngân_hàng_phục_vụ " là một ngân_hàng thương_mại được lựa_chọn trong danh_sách các ngân_hàng thương_mại đủ tiêu_chuẩn thực_hiện việc giao_dịch đối_ngoại , cung_cấp dịch_vụ ngân_hàng cho dự_án nguồn vốn ODA và vốn vay ưu_đãi .  Danh_sách các ngân_hàng thương_mại đủ tiêu_chuẩn do Ngân_hàng Nhà_nước Việt_Nam xác_định và công_bố . 

2 . Tiêu_chuẩn lựa_chọn ngân_hàng_phục_vụ cho chương_trình , dự_án cụ_thể : 

a ) Đáp_ứng đầy_đủ các quy_định của Ngân_hàng Nhà_nước Việt_Nam_về tỷ_lệ đảm_bảo an_toàn tài_chính áp_dụng đối_với các tổ_chức tín_dụng ; 

b ) Có địa_bàn hoạt_động phù_hợp với địa_bàn của chương_trình , dự_án sử_dụng vốn vay ODA và vay ưu_đãi ; 

c ) Tuân_thủ hoặc cam_kết tuân_thủ các quy_định của Chính_phủ , Bộ Tài_chính và quy_định của nhà tài_trợ về quản_lý nguồn vốn ODA , vốn vay ưu_đãi . 

Điều 10 .  Tài_khoản tại ngân_hàng_phục_vụ 

1 . Trừ trường_hợp các dự_án thực_hiện theo phương_thức hỗ_trợ ngân_sách phải mở tài_khoản tại Kho_bạc Nhà_nước nơi giao_dịch để thuận_tiện trong công_tác kiểm_soát chi , rút vốn cho dự_án và hạch_toán ngân_sách nhà_nước , Chủ dự_án hoặc Bộ Tài_chính được mở tài_khoản giao_dịch ( tài_khoản tạm_ứng/tài_khoản đặc_biệt ) tại ngân_hàng_phục_vụ phù_hợp với yêu_cầu thanh_toán của dự_án , quy_định trong Hiệp_định vay/Thỏa_thuận tài_trợ . 

Các dự_án có nhiều nguồn tài_trợ khác nhau phải mở các tài_khoản riêng để theo_dõi từng nguồn vốn rút về . 

Trường_hợp dự_án có nhiều cấp quản_lý thực_hiện và theo thỏa_thuận với nhà tài_trợ có thiết_kế tài_khoản tạm_ứng cấp 2 , chủ dự_án mở tài_khoản tạm_ứng cấp 2 tại chi_nhánh Ngân_hàng_phục_vụ . 

2 . Lãi phát_sinh trên các tài_khoản tạm_ứng/tài_khoản đặc_biệt do chủ dự_án là chủ tài_khoản phải được hạch_toán theo_dõi riêng và trong quá_trình thực_hiện dự_án chỉ được sử_dụng để thanh_toán phí dịch_vụ ngân_hàng của ngân_hàng_phục_vụ . 

Trước ngày 15/02 hàng năm , chủ dự_án có trách_nhiệm báo_cáo Bộ Tài_chính tình_hình sử_dụng lãi phát_sinh trên số_dư tài_khoản tạm_ứng/tài_khoản đặc_biệt của năm trước . 

3 . Xử_lý_số dư lãi tài_khoản tạm_ứng/tài_khoản đặc_biệt : 

a ) Đối_với các dự_án thuộc diện ngân_sách nhà_nước cấp_phát : sau khi dự_án kết_thúc , nếu vẫn còn số_dư lãi tiền gửi , chủ dự_án nộp toàn_bộ số_dư vào ngân_sách nhà_nước . 

b ) Đối_với các dự_án cho vay lại mà chủ dự_án nhận nợ từ khi rút vốn về tài_khoản tạm_ứng/tài_khoản đặc_biệt , lãi phát_sinh trên tài_khoản tạm_ứng/tài_khoản đặc_biệt tại ngân_hàng_phục_vụ là nguồn thu của chủ dự_án hoặc của các tổ_chức tài_chính tín_dụng vay lại vốn vay của Chính_phủ . 

c ) Lãi phát_sinh trên tài_khoản tiền gửi tại ngân_hàng_phục_vụ đối_với các hạn_mức tín_dụng/hợp_phần tín_dụng do các tổ_chức tài_chính , tín_dụng vay lại vốn vay của Chính_phủ và chịu rủi_ro tín_dụng là nguồn thu của tổ_chức tài_chính , tín_dụng và được xử_lý theo <L rel="Reference"> Luật các tổ_chức tín_dụng </L> và các quy_định pháp_luật có liên_quan .
Điều 11 .  Các hình_thức rút vốn 

1 . Đối_với phương_thức hỗ_trợ ngân_sách : 

a ) Rút vốn một lần về ngân_sách nhà_nước : được thực_hiện đối_với các chương_trình hỗ_trợ ngân_sách trực_tiếp hoặc các chương_trình , dự_án hợp_tác khu_vực , toàn_cầu do Chính_phủ trực_tiếp thực_hiện . 

b ) Rút vốn nhiều lần về ngân_sách nhà_nước : được thực_hiện đối_với các chương_trình kèm theo khung chính_sách ;  các chương_trình hạn_mức tín_dụng ;  các chương_trình , dự_án ô ;  hoặc theo phương_thức tài_trợ dựa trên kết_quả của Ngân_hàng Thế_giới ( WB ) . 

2 . Đối_với phương_thức tài_trợ theo chương_trình , dự_án : được thực_hiện theo một hoặc một_số các hình_thức rút vốn sau đây : 

a ) Thanh_toán trực_tiếp/thanh_toán chuyển tiền : 

- Thanh_toán trực_tiếp : là hình_thức mà theo đề_nghị của Bên vay , nhà tài_trợ đồng_ý chuyển tiền thanh_toán trực_tiếp cho nhà_thầu/nhà cung_cấp của dự_án . 

- Thanh_toán chuyển tiền : là hình_thức thanh_toán trực_tiếp và/hoặc thanh_toán hoàn vốn nêu ở điểm c ) dưới đây bằng Đồng Việt_Nam . 

b ) Thanh_toán theo thư cam_kết : là hình_thức thanh_toán mà theo đề_nghị của Bên vay , nhà tài_trợ phát_hành một thư cam_kết sẽ trả lại tiền cho ngân_hàng thương_mại đối_với khoản thanh_toán đã thực_hiện cho nhà_thầu/nhà cung_cấp theo phương_thức thanh_toán Thư_tín_dụng ( L/C ) qua hệ_thống ngân_hàng thương_mại ( ngân_hàng cho vay , ngân_hàng_phục_vụ ) . 

c ) Hoàn vốn : là hình_thức mà nhà tài_trợ thanh_toán tiền từ tài_khoản vốn vay vào tài_khoản do Bên vay chỉ_định , để hoàn lại các khoản chi hợp_lệ do Bên vay/Chủ dự_án đã chi cho dự_án vay .  Các khoản chi hợp_lệ có_thể phát_sinh trước hoặc sau khi ký thỏa_thuận vay nước_ngoài và phải tuân_thủ các quy_định cụ_thể trong thỏa_thuận vay nước_ngoài . 

d ) Tài_khoản tạm_ứng/Tài_khoản đặc_biệt : 

Hình_thức Tài_khoản tạm_ứng là hình_thức nhà tài_trợ tạm_ứng trước một khoản tiền theo đề_nghị của Bên vay , vào một tài_khoản đặc_biệt mở riêng cho dự_án tại một ngân_hàng_phục_vụ Bên vay , để Bên vay chủ_động trong việc thanh_toán cho các khoản chi_tiêu thường_xuyên và hợp_lệ của dự_án , giảm bớt số lần rút vốn vay , nhưng nhà tài_trợ vẫn kiểm_soát chặt_chẽ việc thanh_toán từ tài_khoản đặc_biệt này cho các hoạt_động của dự_án . 

Điều 12 .  Trình_tự và thủ_tục rút vốn đối_với các khoản ODA và vốn vay ưu_đãi theo phương_thức hỗ_trợ ngân_sách 

1 . Đối_với chương_trình kèm theo khung chính_sách , Chủ dự_án , cơ_quan chủ_quản có trách_nhiệm chủ_trì hoặc phối_hợp với Bộ Tài_chính/Ngân_hàng Nhà_nước và các cơ_quan liên_quan để thực_hiện các cam_kết về phần mình theo thỏa_thuận với nhà tài_trợ , để thỏa_mãn điều_kiện tiên_quyết về rút vốn nêu trong các thỏa_thuận vay . 

2 . Đối_với các dự_án/chương_trình hỗ_trợ ngân_sách theo phương_thức giải_ngân dựa trên kết_quả đầu_ra , Chủ dự_án , cơ_quan chủ_quản có trách_nhiệm chủ_trì , phối_hợp với các cơ_quan liên_quan thực_hiện các chỉ_số giải_ngân về phần mình theo thỏa_thuận với nhà tài_trợ để làm cơ_sở rút vốn .  Chủ dự_án được tiếp_nhận vốn tạm_ứng theo quy_định của nhà tài_trợ để thực_hiện các công_việc đã thỏa_thuận nhằm đạt được cam_kết gắn với chỉ_số giải_ngân . 

3 . Chủ dự_án , cơ_quan chủ_quản có trách_nhiệm chủ_trì hoặc phối_hợp với các cơ_quan liên_quan lập báo_cáo , tài_liệu hoặc cung_cấp chứng_từ cụ_thể chứng_minh việc hoàn_thành các cam_kết khung về chính_sách , các tiêu_chí giải_ngân quy_định tại văn_kiện dự_án hoặc thỏa_thuận tài_trợ , để gửi nhà tài_trợ và Bộ Tài_chính phục_vụ yêu_cầu rút vốn . 

4 . Bộ Tài_chính có trách_nhiệm tổng_hợp các hồ_sơ và đơn rút vốn gửi nhà tài_trợ , đồng_thời phối_hợp với Ngân_hàng Nhà_nước , ngân_hàng_phục_vụ và chủ dự_án trong việc chuyển các khoản rút vốn về ngân_sách nhà_nước để sử_dụng theo thỏa_thuận với nhà tài_trợ . 

5 . Đối_với các khoản hỗ_trợ ngân_sách nhà_nước để thực_hiện các chương_trình mục_tiêu quốc_gia , chương_trình hỗ_trợ ngân_sách theo ngành : 

a ) Cơ_quan chủ_quản chương_trình , dự_án có trách_nhiệm thống_nhất với Bộ Tài_chính về thời_điểm rút vốn , số tiền rút và tài_khoản nhận vốn ODA và vốn vay ưu_đãi , đồng_thời phối_hợp với Bộ Tài_chính trong việc lập kế_hoạch phân_bổ và chuyển vốn cho các tiểu dự_án thành_phần thực_hiện chương_trình . 

b ) Vốn ODA , vốn vay ưu_đãi đã rút về ngân_sách để chi_tiêu cho các mục_tiêu , các nội_dung của chương_trình được thực_hiện theo đúng quy_trình về kiểm_soát chi , cấp_phát_thanh_toán vốn ngân_sách nhà_nước theo các quy_định hiện_hành áp_dụng cho các chương_trình mục_tiêu quốc_gia , chương_trình hỗ_trợ ngân_sách theo ngành có liên_quan . 

6 . Hồ_sơ rút vốn : tuân_thủ theo đúng các quy_định , thỏa_thuận với nhà tài_trợ . 

Điều 13 .  Trình_tự và thủ_tục rút vốn đối_với các khoản ODA , vay ưu_đãi theo phương_thức tài_trợ dự_án 

1 . Sau khi nhà tài_trợ thông_báo các điều_kiện tiên_quyết để rút vốn theo quy_định tại các hiệp_định vay/thỏa_thuận tài_trợ đã hoàn_thành , chủ dự_án hoặc ban quản_lý dự_án lập bộ hồ_sơ đề_nghị rút vốn gửi Bộ Tài_chính . 

2 . Bộ hồ_sơ đề_nghị rút vốn được lập căn_cứ vào quy_định cụ_thể theo mẫu của nhà tài_trợ và hướng_dẫn cụ_thể theo từng loại_hình rút vốn nêu tại Điều 14 và Điều 15 Thông_tư này , bao_gồm các loại sau đây : 

a ) Hồ_sơ pháp_lý gửi một lần . 

b ) Hồ_sơ gửi từng lần rút vốn . 

3 . Trong vòng 5 ngày làm_việc kể từ khi nhận đủ bộ hồ_sơ rút vốn hợp_lệ , Bộ Tài_chính ký đơn rút vốn gửi nhà tài_trợ . 

4 . Trong trường_hợp nhà tài_trợ yêu_cầu các tài_liệu bổ_sung , hoặc chỉ chấp_thuận một phần đơn rút vốn , Bộ Tài_chính sẽ thông_báo cho chủ dự_án để phối_hợp xử_lý kịp_thời các yêu_cầu hợp_lý của nhà tài_trợ . 

Điều 14 .  Hồ_sơ pháp_lý gửi một lần 

1 . Chủ dự_án gửi bộ hồ_sơ Hồ_sơ pháp_lý gửi một lần cho Bộ Tài_chính , đồng gửi cho Cơ_quan kiểm_soát chi để làm căn_cứ pháp_lý quản_lý việc rút vốn ODA và vốn vay ưu_đãi cho mỗi chương_trình , dự_án .  Hồ_sơ này bao_gồm các tài_liệu cơ_bản sau đây : 

a ) Thỏa_thuận tài_trợ được ký giữa Chính_phủ Việt_Nam với nhà tài_trợ ( bản dịch bằng tiếng Việt có chữ_ký và dấu của chủ dự_án và chỉ gửi cho cơ_quan kiểm_soát chi ) ; 

b ) Dự_án đầu_tư ( Báo_cáo nghiên_cứu_khả_thi ) và/hoặc Văn_kiện dự_án được cấp có thẩm_quyền phê_duyệt kèm Quyết_định đầu_tư dự_án của cấp có thẩm_quyền ( bản_sao ) ;  Quyết_định phê_duyệt tổng dự_toán ( nếu có ) ; 

c ) Hợp_đồng giữa chủ dự_án và nhà_thầu và các tài_liệu đi kèm hợp_đồng liên_quan đến điều_kiện thanh_toán , trừ các bản_vẽ , các tài_liệu về thiết_kế , kỹ_thuật ( bản_sao ) ;  đối_với hợp_đồng chỉ ký bằng tiếng nước_ngoài thì gửi kèm bản dịch sang tiếng Việt_phần các quy_định về thanh_toán của hợp_đồng , có chữ_ký và đóng_dấu của chủ dự_án ; 

d ) Các thỏa_thuận , thư hoặc văn_bản " ý_kiến không phản_đối " ( no objection ) của nhà tài_trợ ;  thỏa_thuận với nhà_thầu về thực_hiện dự_án ( danh_mục chi_phí hợp_lệ , hợp_đồng ;  bảo_lãnh thực_hiện hợp_đồng ) ;  dự_toán được duyệt đối_với từng hạng_mục , gói_thầu , dự_án được cấp thẩm_quyền phê_duyệt ( đối_với trường_hợp chỉ_định thầu và các công_việc thực_hiện không qua hợp_đồng ) và tài_liệu dự_án liên_quan khác ( nếu có ) ; 

đ ) Kế_hoạch vốn hàng năm được cấp có thẩm_quyền phê_duyệt ; 

e ) Thỏa_thuận cho vay lại ký giữa chủ dự_án và Cơ_quan cho vay lại ( nếu có ) . 

2 . Chủ dự_án chỉ gửi Bộ Tài_chính một lần bản_sao các tài_liệu trên khi lập Bộ hồ_sơ đề_nghị rút vốn lần đầu_tiên .  Chủ dự_án chịu trách_nhiệm trước pháp_luật về tính xác_thực của các bản_sao cung_cấp cho Bộ Tài_chính .  Riêng bản kế_hoạch tài_chính dự_án hàng năm phải gửi bản_gốc cho Bộ Tài_chính và Cơ_quan kiểm_soát chi . 

Điều 15 .  Hồ_sơ gửi từng lần rút vốn 

1 . Thanh_toán trực_tiếp/thanh_toán chuyển tiền ( JICA ) 

a ) Công_văn đề_nghị rút vốn kèm theo Đơn rút vốn , các sao kê theo mẫu và các chứng_từ cần_thiết theo quy_định của nhà tài_trợ ; 

b ) Hóa_đơn/Đề_nghị thanh_toán của Nhà_thầu/Nhà_cung_cấp ; 

c ) Giấy đề_nghị thanh_toán có xác_nhận ( bản_gốc ) của Cơ_quan kiểm_soát chi ; 

d ) Trường_hợp thực_hiện kiểm_soát chi sau , Chủ dự_án cần lưu_ý xử_lý việc rút vốn theo từng giai_đoạn thanh_toán như sau : 

- Trong giai_đoạn thanh_toán giữa kỳ , nếu trị_giá Giấy xác_nhận thanh_toán của Cơ_quan kiểm_soát chi có chênh_lệch với số chi thực_tế đã thanh_toán ở kỳ trước , Chủ dự_án chịu trách_nhiệm điều_chỉnh số chênh_lệch này vào trị_giá thanh_toán của kỳ kế_tiếp . 

- Thanh_toán kỳ cuối : Chủ dự_án gửi Giấy đề_nghị thanh_toán có xác_nhận của Cơ_quan kiểm_soát chi đối_với kỳ thanh_toán trước đó và của kỳ thanh_toán cuối_cùng để đảm_bảo toàn_bộ khối_lượng thanh_toán của Hợp_đồng dự_án đã được kiểm_soát thanh_toán toàn_bộ . 

2 . Thủ_tục Thư cam_kết/Cam_kết đặc_biệt 

a ) Chủ dự_án gửi Bộ Tài_chính bộ hồ_sơ gồm các tài_liệu sau : 

- Công_văn đề_nghị nhà tài_trợ phát_hành thư cam_kết ; 

- Bộ hồ_sơ phát_hành thư cam_kết theo mẫu của nhà tài_trợ và bản_sao L/C đã mở . 

b ) Thủ_tục thanh_toán bằng L/C không cần thư cam_kết : Nếu hợp_đồng thương_mại có điều_khoản thanh_toán bằng L/C không cần thư cam_kết , Chủ dự_án gửi Bộ Tài_chính công_văn đề_nghị mở L/C kèm theo bản_sao hợp_đồng thương_mại và hồ_sơ liên_quan để xem_xét có ý_kiến về việc mở L/C gửi Ban quản_lý dự_án và ngân_hàng_phục_vụ , đồng_thời gửi Thư thông_báo ủy_quyền thanh_toán không hủy ngang cho ngân_hàng được ủy_quyền của nhà tài_trợ để thanh_toán theo L/C . 

Đối_với việc rút vốn nguồn JICA áp_dụng chế_độ kiểm_soát chi sau , sau mỗi lần ký chấp_thuận thanh_toán cho nhà_thầu/tư_vấn , Chủ dự_án gửi bộ hồ_sơ thanh_toán cho Cơ_quan kiểm_soát chi để thực_hiện kiểm_soát chi .  Khi có kết_quả kiểm_soát chi , Chủ dự_án gửi Bộ Tài_chính 1 bản Yêu_cầu thanh_toán ( Claims for Payment ) và 1 bản Giấy đề_nghị thanh_toán có xác_nhận ( bản_gốc ) của Cơ_quan kiểm_soát chi để phục_vụ công_tác theo_dõi , đối_chiếu số_liệu rút vốn với JICA . 

3 . Thủ_tục Hoàn vốn/Hồi_tố 

a ) Chủ dự_án gửi Bộ Tài_chính bộ hồ_sơ rút vốn gồm các tài_liệu sau : 

- Công_văn đề_nghị rút vốn , Đơn rút vốn và sao kê theo mẫu ; 

Đơn rút vốn phải ghi rõ tên và số tài_khoản của từng đơn_vị đã ứng vốn .  Đối_với các khoản do Ngân_sách nhà_nước ứng trước ( vốn chuẩn_bị dự_án , vốn ứng trước để thực_hiện dự_án ) , phải nêu rõ tên và số tài_khoản của cấp ngân_sách nơi ứng vốn . 

- Chứng_từ chuyển tiền chứng_minh khoản thanh_toán đã được thực_hiện cho nhà_thầu/người hưởng lợi và/hoặc Bảng kê xác_nhận đã nhận được vốn thanh_toán của Nhà_thầu/Người hưởng lợi ; 

- Giấy đề_nghị thanh_toán vốn đầu_tư có xác_nhận ( bản_gốc ) của Cơ_quan kiểm_soát chi . 

Trong trường_hợp đặc_biệt theo yêu_cầu của nhà tài_trợ , Bộ Tài_chính có_thể yêu_cầu các tài_liệu bổ_sung . 

b ) Trong trường_hợp rút vốn nguồn JICA : Chủ dự_án gửi Bộ Tài_chính bộ hồ_sơ rút vốn gồm các tài_liệu sau : 

- Hợp_đồng ký giữa chủ đầu_tư và nhà_thầu và các văn_bản phê_duyệt hợp_đồng của phía Việt_Nam và JICA , kèm theo bản dịch sang tiếng Việt có chữ_ký và đóng_dấu của chủ dự_án ; 

- Công_văn đề_nghị rút vốn và các chứng_từ cần_thiết theo quy_định của nhà tài_trợ ; 

- Giấy đề_nghị thanh_toán có xác_nhận ( bản_gốc ) của Cơ_quan kiểm_soát chi . 

4 . Tài_khoản tạm_ứng/Tài_khoản đặc_biệt 

a ) Rút vốn lần đầu về Tài_khoản tạm_ứng ( TKTƯ ) 

Việc rút vốn lần đầu về TKTƯ được thực_hiện căn_cứ trên hạn_mức ( hoặc mức trần ) của TKTƯ quy_định trong Thỏa_thuận vay/Hiệp_định tài_trợ .  Hạn_mức TKTƯ có_thể được quy_định cho 2 cấp ( đối_với dự_án có cấp Trung_ương và cấp địa_phương cùng tham_gia thực_hiện ) , nhưng số vốn rút phải chuyển qua TKTƯ cấp 1 . 

Sau khi Thỏa_thuận vay/Hiệp_định tài_trợ đã có hiệu_lực rút vốn , Chủ dự_án gửi Bộ Tài_chính các tài_liệu sau : ( i ) Công_văn đề_nghị rút vốn , ( ii ) Đơn rút vốn và các sao kê đi kèm theo mẫu của Nhà tài_trợ và ( iii ) Kế_hoạch chi_tiêu theo quy_định nhà tài_trợ , chi_tiết cho giai_đoạn 3 tháng tới , để xem_xét và ký Đơn rút vốn gửi nhà tài_trợ . 

b ) Chi_tiêu từ TKTƯ : thực_hiện theo quy_định tại Điều 16 Thông_tư này . 

Riêng đối_với nguồn vốn vay JICA , chủ dự_án gửi Bộ Tài_chính các tài_liệu sau : 

- Công_văn đề_nghị thanh_toán vốn của chủ chương_trình , dự_án ; 

- Đề_nghị thanh_toán của nhà_thầu/nhà cung_cấp/người thụ_hưởng ; 

- Giấy đề_nghị thanh_toán có xác_nhận ( bản_gốc ) của Cơ_quan kiểm_soát chi đối_với mỗi đợt thanh_toán ( hình_thức kiểm_soát chi trước ) .  Trường_hợp thanh_toán tạm_ứng cần cung_cấp các chứng_từ bảo_lãnh ngân_hàng đối_với khoản tạm_ứng theo quy_định . 

c ) Bổ_sung TKTƯ : 

Để rút vốn bổ_sung TKTƯ ( TKTƯ cấp 1 ) , Chủ dự_án gửi các tài_liệu sau cho Bộ Tài_chính : 

- Công_văn đề_nghị rút vốn bổ_sung TKTƯ ; 

- Kế_hoạch chi_tiêu từ TKTƯ chi_tiết cho giai_đoạn 3 tháng tới ; 

- Đơn rút vốn và các sao kê theo mẫu của nhà tài_trợ ; 

- Sao kê do Chủ dự_án lập , thể_hiện rõ từng khoản chi từ TKTƯ , chi_tiết theo : ngày thanh_toán , số tiền nguyên tệ , số tiền quy_đổi ra VNĐ , tỷ_giá đồng ngoại_tệ/VNĐ , nội_dung thanh_toán , đối_tượng thụ_hưởng ; 

- Giấy đề_nghị thanh_toán vốn đầu_tư có xác_nhận ( bản_gốc ) của Cơ_quan kiểm_soát chi ; 

- Sao kê TKTƯ của ngân_hàng_phục_vụ ( nếu có TKTƯ cấp 2 thì gửi kèm sao kê ) .  Đối_với vốn vay JICA cần cung_cấp chứng_từ chứng_minh việc ngân_hàng_phục_vụ đã chuyển tiền thanh_toán cho người thụ_hưởng . 

Bộ Tài_chính xem_xét ký/đồng ký Đơn rút vốn gửi Nhà tài_trợ để chuyển tiền bổ_sung vào TKTƯ . 

Điều 16 .  Quản_lý rút vốn và sử_dụng vốn ODA , vốn vay ưu_đãi 

1 . Mục_đích kiểm_soát chi 

Để bảo_đảm sử_dụng đúng mục_đích và có hiệu_quả nguồn vốn ODA , vốn vay ưu_đãi của Chính_phủ , việc rút vốn , chi_tiêu và thanh_toán của các dự_án sử_dụng vốn ODA , vốn vay ưu_đãi của Chính_phủ được kiểm_tra , giám_sát như chi_tiêu và sử_dụng ngân_sách nhà_nước ở các cơ_quan , đơn_vị dự_toán ngân_sách , thông_qua việc thực_hiện kiểm_soát chi_tiêu và thanh_toán ( sau đây gọi tắt là kiểm_soát chi ) từ nguồn vốn ODA , vốn vay ưu_đãi của dự_án .  Kiểm_soát chi nhằm đảm_bảo chi_tiêu của dự_án phù_hợp với Hiệp_định/Văn_kiện dự_án/Hợp_đồng sử_dụng nguồn vốn ODA và vốn vay ưu_đãi đã ký_kết và tuân_thủ các quy_định về quản_lý_tài_chính trong nước hiện_hành . 

2 . Nguyên_tắc kiểm_soát chi 

a ) Kiểm_soát chi áp_dụng đối_với mọi hoạt_động chi_tiêu của dự_án . 

b ) Kiểm_soát chi các hồ_sơ đề_nghị thanh_toán để rút vốn ODA , vốn vay ưu_đãi phải căn_cứ vào kế_hoạch giải_ngân vốn nước_ngoài hàng năm được duyệt .  Trong trường_hợp_số rút vốn thực_tế trong năm vượt kế_hoạch giải_ngân vốn nước_ngoài năm được cấp có thẩm_quyền phê_duyệt ( kể_cả trong trường_hợp do chênh_lệch tỷ_giá ) , chậm nhất đến ngày 30/12 chủ dự_án có trách_nhiệm lập và trình cơ_quan chủ_quản phê_duyệt kế_hoạch điều_chỉnh nhằm bổ_sung số vốn tăng thêm trong năm , trên nguyên_tắc tổng giá_trị giải_ngân và thanh_toán lũy kế không vượt quá hạn_mức vốn nước_ngoài của toàn dự_án .  Đối_với vốn đối_ứng , cơ_quan kiểm_soát chi có trách_nhiệm kiểm_soát , xác_nhận trong phạm_vi kế_hoạch vốn đối_ứng được giao . 

c ) Trên_cơ_sở hồ_sơ đề_nghị thanh_toán của chủ dự_án , Cơ_quan kiểm_soát chi căn_cứ vào các điều_khoản thanh_toán được quy_định trong hợp_đồng ( số lần thanh_toán , giai_đoạn thanh_toán , thời_điểm thanh_toán và các điều_kiện thanh_toán ) , hoặc dự_toán vốn đối_với trường_hợp thanh_toán không theo hợp_đồng và giá_trị từng lần thanh_toán , để thực_hiện kiểm_soát chi và thanh_toán cho chủ dự_án .  Chủ dự_án tự chịu trách_nhiệm về tính chính_xác , hợp_pháp của khối_lượng thực_hiện , định_mức , đơn_giá , dự_toán các loại công_việc , chất_lượng công_trình ;  Cơ_quan kiểm_soát chi không chịu trách_nhiệm về các vấn_đề này . 

d ) Cơ_quan kiểm_soát chi có trách_nhiệm kiểm_soát chi hoặc từ_chối xác_nhận kiểm_soát chi trong vòng 5 ngày làm_việc kể từ khi nhận đầy_đủ hồ_sơ , chứng_từ hợp_lệ . 

3 . Cơ_quan kiểm_soát chi : 

a ) Kho_bạc nhà_nước các cấp thực_hiện việc kiểm_soát hồ_sơ thanh_toán của dự_án/hợp_phần dự_án thuộc diện ngân_sách nhà_nước cấp_phát . 

b ) Ngân_hàng Phát_triển Việt_Nam hoặc Cơ_quan cho vay lại khác được Bộ Tài_chính ủy_quyền cho vay lại thực_hiện việc kiểm_soát hồ_sơ thanh_toán của dự_án/hợp_phần dự_án thuộc diện cho vay lại . 

c ) Chương_trình hạn_mức tín_dụng/hợp_phần tín_dụng : 

- Tổ_chức tài_chính , tín_dụng được Bộ Tài_chính ủy_quyền là Cơ_quan cho vay lại không chịu rủi_ro tín_dụng thực_hiện việc kiểm_soát chi đối_với đề_nghị rút vốn và thanh_toán của người vay lại . 

- Tổ_chức tài_chính , tín_dụng vay lại theo các chương_trình , hạn_mức tín_dụng và chịu rủi_ro tín_dụng có trách_nhiệm kiểm_soát chi khi cho vay lại đối_với người vay vốn cuối_cùng . 

d ) Bộ Tài_chính xác_định cơ_quan kiểm_soát chi thích_hợp đối_với các loại chương_trình , dự_án khác chưa được xác_định theo các điểm a ) , b ) và c ) nêu trên , đảm_bảo nguyên_tắc không có hai cơ_quan kiểm_soát chi cùng kiểm_soát một hoạt_động chi_tiêu của dự_án . 

4 . Hình_thức kiểm_soát chi 

a ) " Kiểm_soát chi trước " là việc Cơ_quan kiểm_soát chi kiểm_tra , xác_nhận tính hợp_lệ của khoản chi trước khi Chủ dự_án rút vốn thanh_toán cho nhà_thầu/người thụ_hưởng . 

b ) " Kiểm_soát chi sau " là việc Cơ_quan kiểm_soát chi kiểm_tra , xác_nhận tính hợp_lệ của khoản chi sau khi Chủ dự_án đã rút vốn thanh_toán cho nhà_thầu/người thụ_hưởng . 

Kiểm_soát chi sau được áp_dụng cho mọi đề_nghị thanh_toán , trừ các trường_hợp dưới đây phải thực_hiện kiểm_soát chi trước : 

- Thanh_toán trực_tiếp cho nhà_thầu/nhà cung_cấp đối_với các dự_án hoặc dự_án thành_phần thuộc diện được cấp_phát , trừ các dự_án vốn vay JICA . 

- Thanh_toán trực_tiếp cho nhà_thầu/nhà cung_cấp đối_với các hợp_đồng_thanh_toán một lần hoặc đợt thanh_toán lần cuối của hợp_đồng đối_với hợp_đồng_thanh_toán nhiều lần . 

- Thanh_toán từ tài_khoản cấp hai đối_với dự_án có hai cấp TKTƯ . 

5 . Hồ_sơ và thủ_tục kiểm_soát chi 

a ) Đối_với dự_án/dự_án thành_phần đầu_tư xây_dựng thuộc diện ngân_sách nhà_nước cấp_phát 

- Hồ_sơ và thủ_tục kiểm_soát chi đối_với dự_án đầu_tư xây_dựng thuộc diện ngân_sách nhà_nước cấp_phát : thực_hiện theo quy_định tại <TT rel="Reference"> Thông_tư số 86/2011/TT-BTC ngày 17/6/2011 </TT> của Bộ Tài_chính quy_định về quản_lý , thanh_toán vốn đầu_tư và vốn sự_nghiệp có tính_chất đầu_tư thuộc nguồn ngân_sách nhà_nước và các văn_bản sửa_đổi , bổ_sung , thay_thế ( nếu có ) , nhưng không ràng_buộc bởi thời_hạn phê_duyệt quyết_định đầu_tư dự_án trước ngày 31 tháng 10 năm trước năm kế_hoạch .
- Hồ_sơ , tài_liệu xác_nhận vốn tạm_ứng : ngoài các hồ_sơ , tài_liệu pháp_lý gửi lần đầu , chủ dự_án gửi cơ_quan kiểm_soát chi các tài_liệu sau : 

+ Bảo_lãnh tạm_ứng có giá_trị bằng giá_trị đề_nghị tạm_ứng , có thời_hạn đảm_bảo thu_hồi hết tạm_ứng theo quy_định của hợp_đồng ; 

+ Giấy đề_nghị thanh_toán vốn đầu_tư ;  Giấy rút vốn đầu_tư ( trường_hợp tạm_ứng vốn trong nước ) . 

- Hồ_sơ gửi từng lần rút vốn : Đối_với tiền bảo_hành công_trình đã được cơ_quan kiểm_soát chi xác_nhận từng lần thanh_toán nên khi chuyển tiền bảo_hành không cần xác_nhận lại .  Chủ đầu_tư tự chịu trách_nhiệm về số tiền bảo_hành thanh_toán trả nhà_thầu . 

b ) Đối_với dự_án hoặc các hoạt_động vốn hành_chính sự_nghiệp thuộc diện ngân_sách nhà_nước cấp_phát : thực_hiện theo nguyên_tắc kiểm_soát chi hướng_dẫn tại <TT rel="Reference"> Thông_tư số 161/2012/TT-BTC ngày 2/10/2012 </TT> của Bộ Tài_chính quy_định_chế_độ kiểm_soát , thanh_toán các khoản chi ngân_sách nhà_nước qua Kho_bạc nhà_nước và các văn_bản sửa_đổi , bổ_sung và các quy_định của Thông_tư , căn_cứ vào bộ hồ_sơ rút vốn ODA và vốn vay ưu_đãi quy_định tại Thông_tư này . Trường_hợp Hiệp_định vay/Thỏa_thuận tài_trợ hoặc nhà tài_trợ có quy_định riêng thì thực_hiện theo Hiệp_định vay/Thỏa_thuận tài_trợ hay quy_định đó .
c ) Hồ_sơ và thủ_tục kiểm_soát chi dự_án cho vay lại : 

- Đối_với hạn_mức tín_dụng : 

Hồ_sơ và thủ_tục kiểm_soát chi đối_với các dự_án/hợp_phần cho vay lại theo hạn_mức tín_dụng thực_hiện theo quy_định của các tổ_chức tín_dụng sử_dụng vốn ODA vay lại và phù_hợp với quy_định của hiệp_định tài_trợ và dự_án .  Tổ_chức tín_dụng vay lại vốn ODA chịu trách_nhiệm trước pháp_luật về tính đúng_đắn và hợp_lệ của các khoản cho vay tín_dụng và các khoản chi_tiêu phi tín_dụng trong sao kê chi_tiêu gửi Bộ Tài_chính , khi lập và gửi bộ hồ_sơ rút vốn ngoài nước . 

- Hồ_sơ và thủ_tục kiểm_soát chi dự_án/hợp_phần cho vay lại khác : thực_hiện tương_tự như đối_với các dự_án/dự_án thành_phần đầu_tư xây_dựng thuộc diện ngân_sách nhà_nước cấp_phát . 

Điều 17 .  Mở tài_khoản tại hệ_thống Kho_bạc nhà_nước 

1 . Tài_khoản nguồn vốn ODA , vốn vay ưu_đãi : 

2 . Tài_khoản vốn đối_ứng : chủ dự_án mở tài_khoản tại Kho_bạc nhà_nước nơi giao_dịch để Kho_bạc nhà_nước thực_hiện việc kiểm_soát thanh_toán đối_với chi_tiêu của dự_án , đồng_thời theo_dõi cấp_phát vốn đối_ứng cho dự_án . 

Điều 18 .  Nguyên_tắc hạch_toán ngân_sách nhà_nước 

1 . Nguồn vốn ODA và vốn vay ưu_đãi nước_ngoài phải được hạch_toán đầy_đủ và kịp_thời vào ngân_sách nhà_nước .  Việc hạch_toán ngân_sách nhà_nước do cơ_quan_tài_chính các cấp thực_hiện . 

2 . Hạch_toán ghi thu , ghi chi ngân_sách nhà_nước được thực_hiện trên cơ_sở giá_trị các khoản vốn ODA và vốn vay ưu_đãi nước_ngoài đã giải_ngân và chuyển cho các cơ_quan , tổ_chức , đơn_vị sử_dụng , quy ra Đồng Việt_Nam_theo tỷ_giá hạch_toán do Bộ Tài_chính công_bố hàng tháng ( trong trường_hợp Bộ Tài_chính chuyển cho dự_án bằng ngoại_tệ ) , hoặc theo trị_giá giải_ngân bằng Đồng Việt_Nam cho dự_án ( trong trường_hợp giải_ngân bằng Đồng Việt_Nam ) . Việc hạch_toán ngân_sách nhà_nước đối_với các khoản cho vay lại thực_hiện theo quy_định tại Điều 4 <NĐ rel="Reference"> Nghị_định số 78/2010/NĐ-CP </NĐ> của Chính_phủ .
3 . Số_liệu ghi thu , ghi chi ngân_sách nhà_nước là một trong các căn_cứ để các cơ_quan , tổ_chức , đơn_vị được phép sử_dụng hoặc vay lại vốn vay ODA và vốn vay ưu_đãi nước_ngoài của Chính_phủ thực_hiện hạch_toán và quyết_toán ngân_sách nhà_nước theo quy_định hiện_hành . 

Điều 19 .  Quy_trình hạch_toán ngân_sách nhà_nước 

1 . Đối_với các khoản vay bằng tiền theo hình_thức hỗ_trợ ngân_sách chung : căn_cứ vào chứng_từ nhận tiền/báo có của ngân_hàng_phục_vụ , Kho_bạc nhà_nước hạch_toán thu ngân_sách nhà_nước vốn ODA , vốn vay ưu_đãi theo quy_định ( trường_hợp chuyển ngoại_tệ vào Quỹ ngoại_tệ tập_trung được hạch_toán theo quy_định đối_với các khoản thu ngân_sách nhà_nước bằng ngoại_tệ ) . 

2 . Đối_với các khoản vay bằng tiền theo hình_thức hỗ_trợ ngân_sách theo ngành , lĩnh_vực : căn_cứ vào hiệp_định , thỏa_thuận tài_trợ đã ký và dự_toán giao cho các đơn_vị sử_dụng/thụ_hưởng , Kho_bạc nhà_nước thực_hiện thanh_toán , chi_trả , kiểm_soát chi và hạch_toán chi ngân_sách nhà_nước vốn ODA , vốn vay ưu_đãi theo quy_định như đối_với nguồn vốn ngân_sách nhà_nước . 

3 . Đối_với các khoản vay nước_ngoài cấp_phát cho các dự_án đầu_tư xây_dựng , hành_chính sự_nghiệp của các Bộ , cơ_quan trung_ương : căn_cứ thông_báo giải_ngân của nhà tài_trợ hoặc chứng_từ thanh_toán từ TKTƯ/TKĐB của ngân_hàng_phục_vụ , Bộ Tài_chính thực_hiện ghi thu ngân_sách nhà_nước vốn ODA , vốn vay ưu_đãi , ghi chi cấp_phát vốn đầu_tư xây_dựng , vốn hành_chính sự_nghiệp cho các Bộ , cơ_quan Trung_ương theo mục_lục ngân_sách nhà_nước hiện_hành . 

4 . Đối_với các khoản vay nước_ngoài cấp_phát cho các tỉnh , thành_phố trực_thuộc Trung_ương : căn_cứ thông_báo giải_ngân của nhà tài_trợ , Bộ Tài_chính thực_hiện ghi thu ngân_sách nhà_nước vốn ODA , vốn vay ưu_đãi , ghi chi bổ_sung có mục_tiêu từ ngân_sách trung_ương cho ngân_sách địa_phương thông_qua Sở Tài_chính tỉnh , thành_phố trực_thuộc Trung_ương . Căn_cứ chứng_từ hồ_sơ Bộ Tài_chính gửi , Sở Tài_chính lập lệnh chi tiền cho các đơn_vị sử_dụng vốn tại địa_phương gửi Kho_bạc nhà_nước tỉnh , thành_phố trực_thuộc Trung_ương để thực_hiện cấp_phát ngân_sách theo đúng quy_định của <L rel="Reference"> Luật Ngân_sách nhà_nước </L> .
5 . Đối_với các khoản vay nước_ngoài của Chính_phủ thực_hiện theo cơ_chế Bộ Tài_chính_trực_tiếp cho vay lại đối_với Ủy_ban nhân_dân cấp tỉnh , khu_vực tư_nhân : căn_cứ thông_báo giải_ngân của nhà tài_trợ , Bộ Tài_chính thực_hiện ghi thu ngân_sách nhà_nước vốn ODA , vốn vay ưu_đãi , ghi chi cho vay lại đối_với Cơ_quan cho vay lại được Bộ Tài_chính ủy_quyền . 

6 . Đối_với các khoản vay nước_ngoài của Chính_phủ theo cơ_chế Bộ Tài_chính ủy_quyền cho một tổ_chức tài_chính , tín_dụng là Cơ_quan cho vay lại để cho vay lại các chương_trình , dự_án đầu_tư : căn_cứ Thông_báo giải_ngân của nhà tài_trợ , Bộ Tài_chính thực_hiện ghi thu ngân_sách nhà_nước vốn ODA , vốn vay ưu_đãi , ghi chi cho vay lại đối_với Cơ_quan cho vay lại .  Không phụ_thuộc vào thời_điểm ghi thu ghi chi ngân_sách nhà_nước , Cơ_quan cho vay lại và chủ dự_án vay lại có trách_nhiệm làm thủ_tục nhận nợ ngay khi nhận được bản_sao thông_báo giải_ngân của nhà tài_trợ do Bộ Tài_chính gửi . 

Điều 20 .  Điều_chỉnh số_liệu hạch_toán ngân_sách nhà_nước 

1 . Điều_chỉnh số_liệu hạch_toán ngân_sách nhằm xử_lý chênh_lệch giữa số_liệu ghi thu , ghi chi ngân_sách nhà_nước với quyết_toán thực_tế số_liệu rút vốn và sử_dụng vốn ODA và vay ưu_đãi nước_ngoài , có_thể phát_sinh trong những trường_hợp sau : 

a ) Vốn đã rút nhưng không sử_dụng hết hoặc chi sai mục_đích phải trả lại nhà tài_trợ theo quy_định tại hiệp_định , thỏa_thuận tài_trợ ; 

b ) Chuyển_đổi chủ dự_án theo quyết_định của cơ_quan có thẩm_quyền ; 

c ) Thay_đổi về cơ_chế_tài_chính trong nước theo quyết_định của cấp có thẩm_quyền ( ví_dụ chuyển từ cơ_chế cho vay lại sang cấp_phát từ ngân_sách nhà_nước một phần hoặc toàn_bộ vốn ODA và vay ưu_đãi của dự_án ) ; 

d ) Điều_chỉnh các sai_sót hoặc nhầm_lẫn khác trong quá_trình hạch_toán ngân_sách nhà_nước , căn_cứ vào đối_chiếu số_liệu giữa kho_bạc nhà_nước các cấp với các chủ đầu_tư dự_án . 

2 . Quy_trình và thủ_tục điều_chỉnh : 

a ) Căn_cứ vào đề_nghị điều_chỉnh của cơ_quan chủ_quản và chủ dự_án , kèm theo các tài_liệu , biên_bản , chứng_từ cụ_thể chứng_minh , Bộ Tài_chính ( Cục Quản_lý nợ và Tài_chính đối_ngoại ) tiến_hành rà_soát , đối_chiếu với số_liệu đã hạch_toán ngân_sách nhà_nước và lập Phiếu điều_chỉnh số_liệu ngân_sách gửi Kho_bạc nhà_nước . 

b ) Căn_cứ vào Phiếu điều_chỉnh số_liệu ngân_sách , Kho_bạc nhà_nước thực_hiện hạch_toán điều_chỉnh số_liệu hạch_toán ngân_sách và gửi các liên Phiếu điều_chỉnh số_liệu ngân_sách cho cơ_quan chủ_quản , chủ dự_án để điều_chỉnh các số_liệu hạch_toán tương_ứng trên các báo_cáo kế_toán và quyết_toán vốn nước_ngoài . 

Điều 21 .  Trách_nhiệm bố_trí vốn đối_ứng 

1 . Ngân_sách Trung_ương bố_trí vốn đối_ứng cho các dự_án/dự_án thành_phần thuộc diện cấp_phát từ ngân_sách trung_ương theo <L rel="Reference"> Luật Ngân_sách nhà_nước </L> và do cơ_quan trung_ương là chủ dự_án/dự_án thành_phần quản_lý và thực_hiện . Bộ Kế_hoạch và Đầu_tư , Bộ Tài_chính chịu trách_nhiệm bố_trí đầy_đủ và kịp_thời vốn đối_ứng theo từng nguồn vốn ngân_sách nhà_nước ( xây_dựng cơ_bản , hành_chính sự_nghiệp ) trong kế_hoạch vốn hàng năm , theo phân_công_cụ_thể tại <NĐ rel="Reference"> Nghị_định số 38/2013/NĐ-CP ngày 23/4/2013 </NĐ> của Chính_phủ .
2 . Ngân_sách địa_phương bố_trí vốn đối_ứng cho : 

a ) Các dự_án/dự_án thành_phần thuộc nhiệm_vụ chi của ngân_sách địa_phương theo <L rel="Reference"> Luật Ngân_sách nhà_nước </L> và do cơ_quan địa_phương là chủ dự_án/dự_án thành_phần quản_lý và thực_hiện .
b ) Các dự_án do Ủy_ban nhân_dân cấp tỉnh vay lại vốn vay ODA và vốn vay ưu_đãi của Chính_phủ . 

3 . Tổ_chức tài_chính tín_dụng , doanh_nghiệp thuộc mọi thành_phần kinh_tế chịu trách_nhiệm bố_trí vốn đối_ứng cho : 

a ) Các dự_án/dự_án thành_phần do tổ_chức tài_chính tín_dụng , doanh_nghiệp là chủ dự_án/dự_án thành_phần quản_lý và thực_hiện . 

b ) Các dự_án/dự_án thành_phần do tổ_chức tài_chính tín_dụng , doanh_nghiệp vay lại vốn vay ODA , vốn vay ưu_đãi của Chính_phủ . 

4 . Người hưởng lợi có trách_nhiệm đóng_góp_phần vốn đối_ứng ( bằng tiền , hiện_vật hoặc công_lao_động ) theo thiết_kế của từng chương_trình , dự_án . 

Điều 22 .  Cơ_chế ứng trước vốn 

Ứng trước từ ngân_sách nhà_nước ( ngân_sách trung_ương ) vốn ứng trước để thực_hiện một_số hạng_mục của chương_trình , dự_án thuộc diện cấp_phát từ ngân_sách nhà_nước , trong trường_hợp nguồn vốn ODA và vốn vay ưu_đãi đã được cam_kết tài_trợ và được ghi vào dự_toán ngân_sách nhà_nước trong năm được Quốc_hội quyết_định mà chưa rút được vốn , theo quy_định tại Điều 44 <NĐ rel="Reference"> Nghị_định số 38/2013/NĐ-CP ngày 23/04/2013 </NĐ> của Chính_phủ :
Trên_cơ_sở đề_nghị của cơ_quan chủ_quản , Bộ Kế_hoạch và Đầu_tư chủ_trì , phối_hợp với Bộ Tài_chính xem_xét , quyết_định ứng vốn từ nguồn ngân_sách nhà_nước để thực_hiện chương_trình , dự_án .  Phần vốn ứng trước này phải được thu_hồi hoàn_trả lại ngân_sách nhà_nước ngay khi giải_ngân vốn ODA và vốn vay ưu_đãi từ nhà tài_trợ . 

Điều 23 .  Quy_trình , thủ_tục cho vay lại 

1 . Ký_kết Hợp_đồng/Thỏa_thuận cho vay lại : 

a ) Bộ Tài_chính_trực_tiếp cho vay lại đối_với các tổ_chức tài_chính , tín_dụng ( trường_hợp cho vay lại hạn_mức tín_dụng/hợp_phần tín_dụng và tổ_chức tài_chính , tín_dụng chịu rủi_ro tín_dụng ) hoặc đối_với các chủ dự_án , doanh_nghiệp thuộc mọi thành_phần kinh_tế ( trường_hợp cho vay lại các chương_trình , dự_án đầu_tư cụ_thể , trừ trường_hợp cho vay đối_với hộ sản_xuất , cá_nhân ) , thông_qua việc ký_kết Thỏa_thuận cho vay lại hoặc Hiệp_định vay phụ giữa Bộ Tài_chính và các tổ_chức , đơn_vị này . 

b ) Bộ Tài_chính_trực_tiếp cho Ủy_ban nhân_dân cấp tỉnh vay lại , thông_qua việc ký_kết Biên_bản thỏa_thuận cho vay lại hoặc Hiệp_định vay phụ giữa Bộ Tài_chính và Ủy_ban nhân_dân cấp tỉnh . 

Biên_bản thỏa_thuận cho vay lại hoặc Hiệp_định vay phụ nêu tại điểm a ) và b ) trên được lập cho từng chương_trình , dự_án cho vay lại cụ_thể và theo mẫu thống_nhất với nhà tài_trợ ( nếu có ) . 

c ) Bộ Tài_chính ủy_quyền cho tổ_chức tài_chính , tín_dụng làm Cơ_quan cho vay lại để thực_hiện các chương_trình , dự_án đầu_tư cụ_thể ( trường_hợp tổ_chức tài_chính , tín_dụng không chịu rủi_ro tín_dụng ) , thông_qua việc ký_kết Hợp_đồng ủy_quyền cho vay lại giữa Bộ Tài_chính và Cơ_quan cho vay lại . 

Hợp_đồng ủy_quyền cho vay lại được lập theo Mẫu Hợp_đồng ủy_quyền cho vay lại , quy_định tại Phụ_lục 2 <NĐ rel="Reference"> Nghị_định số 78/2010/NĐ-CP ngày 14/7/2010 </NĐ> của Chính_phủ .
2 . Lập kế_hoạch thu_hồi nợ cho vay lại : 

a ) Đối_với các khoản Bộ Tài_chính cho vay lại trực_tiếp : Bộ Tài_chính xác_định kế_hoạch thu_hồi nợ , kế_hoạch thu phí cho vay lại hàng quý và cả năm , căn_cứ vào các quy_định tại các thỏa_thuận cho vay lại hoặc hiệp_định vay phụ đã ký_kết . 

b ) Đối_với các khoản Bộ Tài_chính ủy_quyền cho Cơ_quan cho vay lại thu : Cơ_quan cho vay lại có trách_nhiệm lập kế_hoạch thu_hồi vốn cho vay lại , kế_hoạch thu phí cho vay lại hàng quý và cả năm , căn_cứ vào các quy_định tại các hợp_đồng ủy_quyền cho vay lại đã ký_kết , gửi cho Bộ Tài_chính để tổng_hợp . 

3 . Tổ_chức công_tác thu_hồi nợ : 

a ) Tài_khoản thu_hồi nợ : Các khoản thu_hồi nợ cho vay lại ( gốc , lãi , phí cho vay lại ) được hoàn_trả trực_tiếp vào tài_khoản giao_dịch bằng ngoại_tệ và Đồng Việt_Nam của Quỹ_tích lũy trả nợ mở tại Sở Giao_dịch Kho_bạc Nhà_nước . 

b ) Tháng 6 và tháng 12 hàng năm , các cơ_quan , tổ_chức , doanh_nghiệp và Ủy_ban nhân_dân cấp tỉnh là Người vay lại trực_tiếp vốn vay nước_ngoài của Chính_phủ chịu trách_nhiệm báo_cáo và đối_chiếu số_liệu hoàn_trả nợ của các chương_trình , dự_án cho vay lại với Bộ Tài_chính ( Quỹ_tích lũy trả nợ ) . 

c ) Cơ_quan cho vay lại có trách_nhiệm báo_cáo tình_hình thực_hiện kế_hoạch thu_hồi vốn cho vay lại , kế_hoạch thu phí cho vay lại định_kỳ hàng quý và cả năm và tình_hình hoàn_trả Quỹ_tích lũy trả nợ theo từng chương_trình , dự_án vay lại gửi Bộ Tài_chính ( Quỹ_tích lũy trả nợ ) .  Thời_hạn báo_cáo là ngày 15 của tháng đầu quý tiếp_theo đối_với báo_cáo quý và trước ngày 31/01 của năm tiếp_theo đối_với báo_cáo năm .  Báo_cáo năm về tình_hình thu_hồi vốn gốc , lãi cho vay lại và thu phí cho vay lại , do Cơ_quan cho vay lại lập và tổng_hợp theo từng chương_trình , dự_án cho vay lại , là căn_cứ để Bộ Tài_chính ( Quỹ_tích lũy trả nợ ) đối_chiếu và xác_nhận số_liệu về các khoản thu_hồi cho vay lại hàng năm với Cơ_quan cho vay lại . 

Điều 24 .  Xử_lý rủi_ro cho vay lại 

Trình_tự , thủ_tục và thẩm_quyền xử_lý rủi_ro cho vay lại được quy_định cụ_thể tại Điều 23 <NĐ rel="Reference"> Nghị_định số 78/2010/NĐ-CP ngày 14/7/2010 </NĐ> của Chính_phủ .
Cơ_quan chủ_quản phối_hợp với Bộ Tài_chính , Cơ_quan cho vay lại trong việc đánh_giá , xếp_hạng và phân_loại nợ bị rủi_ro theo quy_định tại Quy_chế quản_lý và xử_lý rủi_ro đối_với danh_mục nợ công ban_hành kèm theo <QĐ rel="Reference"> Quyết_định số 56/2012/QĐ-TTg ngày 21/12/2012 </QĐ> của Thủ_tướng Chính_phủ .
Điều 25 .  Kế_toán dự_án ODA , vốn vay ưu_đãi 

1 . Nguyên_tắc kế_toán : 

Các đơn_vị sử_dụng vốn ODA , vốn vay ưu_đãi phải đảm_bảo : 

a ) Tuân_thủ các quy_định của <L rel="Reference"> Luật Kế_toán </L> , Chuẩn_mực kế_toán Việt_Nam và các chế_độ kế_toán hiện_hành của Việt_Nam ;
b ) Tuân_thủ các quy_định về kế_toán của nhà tài_trợ được quy_định trong hiệp_định vay , thỏa_thuận tài_trợ hoặc trong văn_kiện dự_án ( nếu có ) ; 

2 . Tổ_chức bộ_máy kế_toán 

Tùy_thuộc quy_mô của dự_án , hình_thức quản_lý dự_án để tổ_chức bộ_máy kế_toán phù_hợp . 

a ) Trường_hợp dự_án không thành_lập Ban Quản_lý dự_án , hoặc có thành_lập Ban quản_lý dự_án nhưng không tổ_chức bộ_máy kế_toán riêng : chủ dự_án được sử_dụng bộ_máy kế_toán và hạch_toán chung trên cùng hệ_thống sổ kế_toán của đơn_vị , kế_toán đơn_vị đồng_thời là kế_toán dự_án để thực_hiện các công_việc kế_toán của dự_án , nhưng phải hạch_toán tách_bạch tài_khoản , nguồn vốn và các khoản thu , chi của dự_án . 

b ) Trường_hợp dự_án có quy_mô lớn , có thành_lập ban quản_lý dự_án ( có tư_cách pháp_nhân độc_lập , có con_dấu riêng ) : ban quản_lý dự_án quyết_định thành_lập Phòng hoặc Bộ_phận kế_toán riêng và thực_hiện bổ_nhiệm kế_toán_trưởng ( hoặc thuê kế_toán_trưởng ) hoặc phụ_trách kế_toán theo quy_định hiện_hành . 

3 . Chế_độ kế_toán áp_dụng 

a ) Đối_với các trường_hợp quy_định tại điểm a ) , khoản 2 Điều này : áp_dụng chế_độ kế_toán mà đơn_vị thực_hiện dự_án đang áp_dụng ( chế_độ kế_toán doanh_nghiệp , chế_độ kế_toán HCSN hoặc chế_độ kế_toán khác phù_hợp ) . 

b ) Đối_với các trường_hợp quy_định tại điểm b ) , khoản 2 Điều này : căn_cứ vào tính_chất sử_dụng vốn , hình_thức quản_lý dự_án , loại_hình đơn_vị sử_dụng vốn để áp_dụng chế_độ kế_toán phù_hợp . 

Điều 26 .  Kiểm_toán báo_cáo tài_chính 

1 . Kiểm_toán báo_cáo tài_chính năm của dự_án ODA , vốn vay ưu_đãi nhằm kiểm_tra và xác_nhận tính trung_thực và hợp_lý của báo_cáo tài_chính dự_án trong một năm tài_chính . 

2 . Báo_cáo tài_chính hàng năm của dự_án tài_trợ bằng nguồn vốn ODA , nguồn vốn vay ưu_đãi phải được kiểm_toán bởi Kiểm_toán nhà_nước hoặc Kiểm_toán độc_lập theo thỏa_thuận với nhà tài_trợ .  Trường_hợp dự_án tài_trợ bằng nguồn vốn ODA , nguồn vốn vay ưu_đãi đã có trong thông_báo kế_hoạch kiểm_toán hàng năm của cơ_quan Kiểm_toán nhà_nước và được nhà tài_trợ chấp_thuận thì báo_cáo tài_chính năm đó không bắt_buộc phải kiểm_toán độc_lập . 

3 . Việc kiểm_toán báo_cáo tài_chính phải tuân_thủ các quy_định của pháp_luật hiện_hành trừ trường_hợp các thỏa_thuận giữa Chính_phủ với nhà tài_trợ có quy_định khác . 

4 . Các doanh_nghiệp kiểm_toán được lựa_chọn thực_hiện kiểm_toán dự_án là các doanh_nghiệp kiểm_toán độc_lập hoạt_động hợp_pháp tại Việt_Nam , được Bộ Tài_chính cấp Giấy chứng_nhận đủ điều_kiện kinh_doanh dịch_vụ kiểm_toán . 

5 . Trường_hợp nhà tài_trợ có quy_định , có_thể yêu_cầu thuê kiểm_toán báo_cáo tài_chính đối_với từng hạng_mục công_trình , công_trình , công_việc đã hoàn_thành . 

6 . Chủ dự_án có trách_nhiệm gửi Báo_cáo kiểm_toán do đơn_vị kiểm_toán độc_lập thực_hiện đối_với báo_cáo tài_chính hàng năm của dự_án cho Kiểm_toán Nhà_nước . 

Điều 27 .  Quyết_toán 

1 . Quyết_toán năm : 

a ) Các dự_án vốn sự_nghiệp sử_dụng vốn ODA , vốn vay ưu_đãi thực_hiện quyết_toán hàng năm theo quy_định tại <TT rel="Reference"> Thông_tư số 01/2007/TT-BTC ngày 2/1/2007 </TT> của Bộ Tài_chính hướng_dẫn xét_duyệt , thẩm_định và thông_báo quyết_toán năm đối_với các cơ_quan hành_chính , đơn_vị sự_nghiệp , tổ_chức được ngân_sách nhà_nước hỗ_trợ và ngân_sách các cấp , và các văn_bản bổ_sung , sửa_đổi hoặc thay_thế Thông_tư này .
b ) Các dự_án đầu_tư xây_dựng sử_dụng vốn ODA , vốn vay ưu_đãi thực_hiện quyết_toán hàng năm theo quy_định tại <TT rel="Reference"> Thông_tư số 210/2010/TT-BTC ngày 20/12/2010 </TT> của Bộ Tài_chính quy_định về việc quyết_toán vốn đầu_tư xây_dựng cơ_bản thuộc nguồn vốn ngân_sách nhà_nước theo niên độ ngân_sách hàng năm và các văn_bản bổ_sung , sửa_đổi hoặc thay_thế Thông_tư này .
2 . Quyết_toán kết_thúc dự_án : 

a ) Các dự_án đầu_tư có sử_dụng vốn ODA , vốn vay ưu_đãi khi hoàn_thành phải thực_hiện quyết_toán dự_án theo <TT rel="Reference"> Thông_tư số 19/2011/TT-BTC ngày 14/02/2011 </TT> của Bộ Tài_chính quy_định về quyết_toán dự_án hoàn_thành thuộc nguồn vốn Nhà_nước và các văn_bản sửa_đổi , bổ_sung hoặc thay_thế Thông_tư này .
b ) Đối_với các dự_án chấm_dứt hoạt_động hoặc có quyết_định giải_thể , sát nhập trong năm ngân_sách , giám_đốc dự_án và người phụ_trách kế_toán phải chịu trách_nhiệm quyết_toán dự_án hoàn_thành đến thời_điểm chấm_dứt hoạt_động , giải_thể , sát nhập , mới được điều_chuyển đi công_tác khác và chịu trách_nhiệm trước pháp_luật về những sai_phạm ( nếu có ) trong thời_gian thực_hiện nhiệm_vụ trên . 

c ) Đối_với chương_trình/dự_án ô gồm nhiều dự_án thành_phần độc_lập , chủ dự_án làm thủ_tục trình_duyệt quyết_toán dự_án thành_phần theo quy_định và gửi kết_quả cho cơ_quan chủ_quản chương_trình/dự_án ô để tổng_hợp báo_cáo quyết_toán của toàn chương_trình . 

Điều 28 .  Báo_cáo tình_hình giải_ngân 

1 . Chủ dự_án lập và gửi Bộ Tài_chính Báo_cáo sao kê rút vốn vay nước_ngoài theo mẫu tại Phụ_lục 1 Thông_tư này khi làm thủ_tục rút vốn vay nước_ngoài theo các hình_thức quy_định tại Điều 15 Thông_tư này để làm cơ_sở ghi thu ghi chi ngân_sách nhà_nước . 

2 . Chủ dự_án gửi Báo_cáo kết_thúc giải_ngân đối_với chương_trình/dự_án cho Bộ Tài_chính trong vòng 30 ngày kể từ khi đóng khoản vay , khoản tài_trợ , chi_tiết theo mẫu quy_định tại Phụ_lục 2 của Thông_tư này để làm cơ_sở quyết_toán dự_án . 

3 . Chủ dự_án lập và gửi các báo_cáo tài_chính cho nhà tài_trợ theo quy_định tại văn_kiện dự_án , hiệp_định vay/thỏa_thuận tài_trợ đã ký_kết , đồng gửi cho cơ_quan chủ_quản và cơ_quan Tài_chính đồng cấp để theo_dõi và chỉ_đạo kịp_thời công_tác quản_lý_tài_chính đối_với dự_án . 

4 . Cơ_quan chủ_quản có trách_nhiệm lập , tổng_hợp và cung_cấp cho Bộ Tài_chính các báo_cáo về nợ công 6 tháng và cả năm , theo mẫu biểu quy_định tại <TT rel="Reference"> Thông_tư số 53/2011/TT-BTC ngày 27/4/2011 </TT> của Bộ Tài_chính hướng_dẫn mẫu biểu báo_cáo và công_khai_thông_tin về nợ công và nợ nước_ngoài của quốc_gia .
Điều 29 .  Kiểm_tra 

Cơ_quan_tài_chính các cấp , cơ_quan chủ_quản dự_án có_thể độc_lập hoặc phối_hợp với các cơ_quan liên_quan thực_hiện việc kiểm_tra định_kỳ hoặc đột_xuất đối_với các dự_án có sử_dụng nguồn vốn ODA và vay ưu_đãi nước_ngoài về việc chấp_hành các quy_định quản_lý_tài_chính được quy_định tại Thông_tư này . 

Điều 30 .  Quản_lý_tài_sản 

Việc quản_lý , sử_dụng và xử_lý_tài_sản đầu_tư , trang_bị từ các dự_án sử_dụng nguồn vốn ODA và nguồn vốn vay ưu_đãi của các nhà tài_trợ , được thực_hiện theo quy_định của Thủ_tướng Chính_phủ và hướng_dẫn của Bộ Tài_chính về việc quản_lý , sử_dụng tài_sản của các dự_án sử_dụng vốn nhà_nước hiện_hành . 

Điều 31 .  Chính_sách thuế 

1 . Chính_sách thuế đối_với các chương_trình , dự_án sử_dụng nguồn vốn ODA và vốn vay ưu_đãi của các nhà tài_trợ được thực_hiện theo hướng_dẫn riêng của Bộ Tài_chính . 

2 . Chính_sách thuế áp_dụng đối_với chương_trình , dự_án của khu_vực kinh_tế tư_nhân sử_dụng nguồn vốn ODA , vốn vay ưu_đãi nước_ngoài của các nhà tài_trợ : Cơ_quan chủ_quản chương_trình , dự_án có mục_tiêu hỗ_trợ khu_vực kinh_tế tư_nhân , tổ_chức tài_chính , tín_dụng cho vay lại chương_trình , hạn_mức tín_dụng cho khu_vực kinh_tế tư_nhân , hoặc cơ_quan có thẩm_quyền cho phép khu_vực kinh_tế tư_nhân tiếp_cận từ nguồn vốn ODA , vốn vay ưu_đãi nước_ngoài của Chính_phủ có trách_nhiệm thông_báo hoặc xác_nhận hình_thức cung_cấp vốn ODA và vốn vay ưu_đãi đối_với từng chương_trình , dự_án cụ_thể cho cơ_quan thuế để áp_dụng các chính_sách thuế đối_với các chương_trình , dự_án sử_dụng nguồn vốn ODA và vốn vay ưu_đãi của các nhà tài_trợ của khu_vực kinh_tế tư_nhân . 

Điều 32 .  Sổ_tay Quản_lý_tài_chính 

Ngoài các quy_định tại Thông_tư này , Bộ Tài_chính phối_hợp với các nhà tài_trợ ( nếu có yêu_cầu ) xuất_bản Sổ_tay quản_lý_tài_chính .  Các Sổ_tay này là tài_liệu tham_khảo về nghiệp_vụ chuyên_môn và nhằm hỗ_trợ cho các tổ_chức , cá_nhân tham_gia quản_lý và thực_hiện chương_trình , dự_án sử_dụng vốn ODA và vốn vay ưu_đãi . 

Điều 33 .  Hiệu_lực thi_hành 

1 . Thông_tư này có hiệu_lực thi_hành kể từ ngày 15/02/2013 và thay_thế các <TT rel="Replace"> Thông_tư số 108/2007/TT-BTC ngày 7/9/2007 </TT> của Bộ Tài_chính hướng_dẫn chế_độ quản_lý_tài_chính nhà_nước đối_với các chương_trình , dự_án ODA ; <TT rel="Replace"> Thông_tư số 40/2011/TT-BTC ngày 22/3/2011 </TT> sửa_đổi , bổ_sung một_số điểm của <TT rel="Others"> Thông_tư số 108/2007/TT-BTC ngày 7/9/2007 </TT> và <TT rel="Replace"> Thông_tư số 107/2011/TT-BTC ngày 20/7/2011 </TT> sửa_đổi Điều 1 <TT rel="Others"> Thông_tư số 40/2011/TT-BTC ngày 22/3/2011 </TT> .
2 . Trong quá_trình thực_hiện , nếu các văn_bản quy_phạm pháp_luật được dẫn chiếu để áp_dụng tại Thông_tư này được sửa_đổi , bổ_sung hoặc thay_thế bằng văn_bản mới thì sẽ áp_dụng theo các văn_bản mới_đó . 

3 . Trong quá_trình thực_hiện , nếu có vướng_mắc hoặc chưa được hướng_dẫn tại Thông_tư này , đề_nghị các cơ_quan , đơn_vị có liên_quan phản_ánh kịp_thời cho Bộ Tài_chính để hướng_dẫn , phối_hợp giải_quyết ./. 