Thông tư Quy định việc xuất bản tài liệu không kinh doanh

Căn_cứ <L rel="Pursuant"> Luật_Xuất_bản ngày 03 tháng 12 năm 2004 </L> và <L rel="Pursuant"> Luật sửa_đổi , bổ_sung một_số điều của <L rel="Others"> Luật_Xuất_bản </L> ngày 03 tháng 6 năm 2008 </L> ;
Căn_cứ <NĐ rel="Pursuant"> Nghị_định số 111/2005/NĐ-CP ngày 26 tháng 8 năm 2005 </NĐ> của Chính_phủ quy_định chi_tiết và hướng_dẫn thi_hành một_số điều của <L rel="Others"> Luật_Xuất_bản </L> ;
Căn_cứ <NĐ rel="Pursuant"> Nghị_định số 11/2009/NĐ-CP ngày 10 tháng 02 năm 2009 </NĐ> sửa_đổi , bổ_sung <NĐ rel="Others"> Nghị_định số 111/2005/NĐ-CP ngày 26 tháng 8 năm 2005 </NĐ> của Chính_phủ quy_định chi_tiết và hướng_dẫn thi_hành một_số điều của <L rel="Others"> Luật_Xuất_bản </L> ;
Căn_cứ <NĐ rel="Pursuant"> Nghị_định số 187/2007/NĐ-CP ngày 25 tháng 12 năm 2007 </NĐ> của Chính_phủ quy_định chức_năng , nhiệm_vụ , quyền_hạn và cơ_cấu tổ_chức của Bộ Thông_tin và Truyền_thông ;
Điều 1 .  Phạm_vi điều_chỉnh 

Thông_tư này quy_định việc xuất_bản tài_liệu không kinh_doanh ( tài_liệu không bán , tài_liệu phát miễn_phí , tài_liệu lưu_hành nội_bộ-sau đây gọi tắt là tài_liệu ) không thực_hiện qua nhà xuất_bản mà do cơ_quan quản_lý nhà_nước về hoạt_động xuất_bản cấp phép . 

Điều 2 .  Đối_tượng áp_dụng 

1 . Cơ_quan nhà_nước , tổ_chức chính_trị , tổ_chức chính_trị-xã_hội , tổ_chức chính_trị-xã_hội – nghề_nghiệp , tổ_chức xã_hội – nghề_nghiệp , đơn_vị sự_nghiệp , đơn_vị vũ_trang nhân_dân , tổ_chức kinh_tế và doanh_nghiệp 100 % vốn nước_ngoài tại Việt_Nam ( sau đây gọi tắt là cơ_quan , tổ_chức Việt_Nam ) ; 

2 . Cơ_quan , tổ_chức nước_ngoài , tổ_chức quốc_tế ( sau đây gọi tắt là cơ_quan , tổ_chức nước_ngoài ) ; 

3 . Cơ_quan quản_lý nhà_nước về hoạt_động xuất_bản : Cục Xuất_bản ( Bộ Thông_tin và Truyền_thông ) ;  Sở Thông_tin và Truyền_thông các tỉnh , thành_phố trực_thuộc trung_ương ( sau đây gọi tắt là cơ_quan cấp phép xuất_bản ) . 

Điều 3 .  Thẩm_quyền của cơ_quan cấp phép xuất_bản 

1 . Cục Xuất_bản ( Bộ Thông_tin và Truyền_thông ) cấp giấy_phép xuất_bản cho cơ_quan , tổ_chức Việt_Nam ở trung_ương và cơ_quan , tổ_chức nước_ngoài những loại tài_liệu có nội_dung sau : 

a ) Tài_liệu tuyên_truyền , cổ_động phục_vụ nhiệm_vụ chính_trị , các ngày kỷ_niệm lớn và các sự_kiện trọng_đại của đất_nước ; 

b ) Tài_liệu hướng_dẫn học_tập và thi_hành chủ_trương đường_lối , các chỉ_thị , nghị_quyết của Đảng , pháp_luật của Nhà_nước ; 

c ) Tài_liệu hướng_dẫn kỹ_thuật sản_xuất , các biện_pháp phòng_chống thiên_tai , dịch_bệnh và bảo_vệ môi_trường ; 

d ) Kỷ_yếu hội_thảo , kỷ_yếu hội_nghị , kỷ_yếu ngành_nghề của các cơ_quan , tổ_chức Việt_Nam ; 

đ ) Tài_liệu của các cơ_quan , tổ_chức nước_ngoài . 

2 . Sở Thông_tin và Truyền_thông các tỉnh , thành_phố trực_thuộc trung_ương cấp giấy_phép xuất_bản cho cơ_quan , tổ_chức Việt_Nam đóng tại địa_phương những loại tài_liệu có nội_dung sau : 

a ) Tài_liệu tuyên_truyền , cổ_động phục_vụ nhiệm_vụ chính_trị , các ngày kỷ_niệm lớn và các sự_kiện trọng_đại của đất_nước ( trong đó bao_gồm tài_liệu về lịch_sử Đảng , chính_quyền của địa_phương ) ; 

b ) Tài_liệu hướng_dẫn học_tập và thi_hành chủ_trương đường_lối , các chỉ_thị , nghị_quyết của Đảng , pháp_luật của Nhà_nước phục_vụ địa_phương ; 

c ) Tài_liệu hướng_dẫn kỹ_thuật sản_xuất , các biện_pháp phòng_chống thiên_tai , dịch_bệnh và bảo_vệ môi_trường phục_vụ địa_phương ; 

d ) Kỷ_yếu hội_thảo , kỷ_yếu hội_nghị , kỷ_yếu ngành_nghề của các cơ_quan , tổ_chức Việt_Nam đóng tại địa_phương . 

Điều 4 .  Hình_thức tài_liệu xuất_bản 

1 . Sách ; 

2 . Băng , đĩa ; 

3 . Tranh , ảnh , áp_phích , tờ rời , tờ_gấp . 

Điều 5 .  Hồ_sơ , trình_tự , cách_thức đề_nghị cấp giấy_phép 

1 . Đơn đề_nghị cấp giấy_phép xuất_bản tài_liệu không kinh_doanh theo mẫu tại phụ_lục số 1 ban_hành kèm theo Thông_tư này .  Trong đơn phải điền đầy_đủ các thông_tin yêu_cầu , có chữ_ký của thủ_trưởng cơ_quan và đóng_dấu của cơ_quan , tổ_chức đứng_tên đề_nghị cấp giấy_phép ; 

2 . Hai bản_thảo tài_liệu có đóng_dấu tại trang tên sách và dấu giáp_lai của cơ_quan , tổ_chức đề_nghị cấp giấy_phép ;  trường_hợp tài_liệu bằng tiếng nước_ngoài , tiếng dân_tộc_thiểu_số Việt_Nam phải kèm theo bản dịch tiếng Việt ; 

3 . Đối_với cơ_quan tổ_chức Việt_Nam không phải là cơ_quan nhà_nước ;  cơ_quan , tổ_chức nước_ngoài thì ngoài hồ_sơ quy_định tại khoản 1 , 2 Điều này phải xuất_trình kèm theo bản_sao có công_chứng quyết_định thành_lập ( hoặc giấy_phép hoạt_động ) do cơ_quan quản_lý nhà_nước có thẩm_quyền của Việt_Nam cấp ; 

4 . Đối_với các tài_liệu là kỷ_yếu ngoài hồ_sơ quy_định tại khoản 1 , 2 Điều này phải có xác_nhận của cơ_quan chủ_quản hoặc cơ_quan có thẩm_quyền vào đơn đề_nghị cấp giấy_phép ; 

5 . Đối_với tài_liệu về lịch_sử Đảng , chính_quyền của địa_phương ngoài hồ_sơ quy_định tại khoản 1 , 2 Điều này phải có văn_bản thẩm_định nội_dung của cơ_quan Đảng , chính_quyền cấp trên ( theo yêu_cầu của cơ_quan cấp phép xuất_bản ) . 

Điều 6 .  Trách_nhiệm của cơ_quan , tổ_chức được cấp phép xuất_bản 

1 . Chỉ đề_nghị cấp giấy_phép xuất_bản tài_liệu đúng với chức_năng , nhiệm_vụ của cơ_quan , tổ_chức đã được cấp phép hoạt_động . 

2 . Đứng_tên chịu trách_nhiệm xuất_bản trên tài_liệu ; thực_hiện việc ghi thông_tin trên tài_liệu xuất_bản theo đúng quy_định tại Điều 26 <L rel="Reference"> Luật_Xuất_bản 2004 </L> và Điều 1 <L rel="Reference"> Luật sửa_đổi bổ_sung một_số điều của <L rel="Others"> Luật_Xuất_bản 2008 </L> </L> ;
3 . In đúng bản_thảo đã được cơ_quan cấp phép xuất_bản đóng_dấu ;  in đúng cơ_sở in , số bản in và phát_hành đúng phạm_vi , đối_tượng ghi trong giấy_phép ; 

4 . Trên_tài_liệu không được thể_hiện giá bán dưới mọi hình_thức ; 

5 . Chỉ được quảng_cáo về sản_phẩm , dịch_vụ và hoạt_động của cơ_quan , tổ_chức xuất_bản tài_liệu đó theo quy_định tại Điều 29 <L rel="Reference"> Luật_Xuất_bản 2004 </L> ;
6 . Chấp_hành các quy_định về quyền tác_giả theo quy_định của pháp_luật về sở_hữu_trí_tuệ ; 

7 . Ít_nhất 10 ngày trước ngày phát_hành , cơ_quan , tổ_chức được cấp giấy_phép xuất_bản nộp lưu_chiểu tài_liệu cho cấp phép xuất_bản theo quy_định pháp_luật về xuất_bản ; 

8 . Chịu trách_nhiệm trước pháp_luật về những vi_phạm của tài_liệu xuất_bản theo quy_định của <L rel="Reference"> Luật_Xuất_bản </L> .
Điều 7 .  Trách_nhiệm của cơ_quan cấp phép xuất_bản 

1 . Trong thời_hạn 10 ngày kể từ ngày nhận đủ hồ_sơ hợp_lệ , cơ_quan cấp phép xuất_bản phải cấp giấy_phép xuất_bản tài_liệu không kinh_doanh theo mẫu tại phụ_lục số 2 và số 3 ban_hành kèm theo Thông_tư này ;  đóng_dấu vào 01 bản_thảo tài_liệu gửi kèm theo giấy_phép ;  trường_hợp không cấp giấy_phép phải có văn_bản nêu rõ lý_do ; 

2 . Nhận và kiểm_tra tài_liệu lưu_chiểu ; trường_hợp phát_hiện tài_liệu vi_phạm thì xử_lý theo thẩm_quyền quy_định tại <L rel="Reference"> Luật_Xuất_bản </L> hoặc chuyển_giao cho cơ_quan_chức_năng xử_lý theo quy_định của pháp_luật .
Điều 8 .  Phí và lệ_phí 

1 . Việc thu phí và lệ_phí cấp giấy_phép xuất_bản tài_liệu không kinh_doanh thực_hiện theo quy_định pháp_luật về phí và lệ_phí ; 

2 . Kinh_phí đọc tài_liệu lưu_chiểu của cơ_quan cấp phép xuất_bản thực_hiện theo quy_định tại <TT rel="Reference"> Thông_tư liên Bộ số 01/2007/TTLT-BVHTT-BTC ngày 22 tháng 01 năm 2007 </TT> của Bộ Văn_hóa – Thông_tin ( nay là Bộ Thông_tin và Truyền_thông ) và Bộ Tài_chính hướng_dẫn định_mức và chế_độ thù_lao đọc xuất_bản_phẩm lưu_chiểu .
Điều 9 .  Hiệu_lực thi_hành 

Thông_tư này có hiệu_lực thi_hành từ ngày 01 tháng 3 năm 2011 . 

Trong quá_trình thực_hiện , nếu có vướng_mắc đề_nghị các cơ_quan , tổ_chức phản_ánh bằng văn_bản về Bộ Thông_tin và Truyền_thông ( qua Cục Xuất_bản ) để xem_xét , giải_quyết ./. 