Thông tư Hướng dẫn thi hành một số điều của Nghị định số 40/2009/NĐ-CP ngày 24/4/2009 của Chính phủ quy định về xử phạt vi phạm hành chính trong lĩnh vực thú y

Căn_cứ <PL rel="Pursuant"> Pháp_lệnh Thú_y ngày 29 tháng 4 năm 2004 </PL> ;
Căn_cứ <PL rel="Pursuant"> Pháp_lệnh Xử_lý vi_phạm hành_chính năm 2002 </PL> và <PL rel="Others"> Pháp_lệnh Sửa_đổi , bổ_sung một_số điều của <PL rel="Others"> Pháp_lệnh Xử_lý vi_phạm hành_chính </PL> năm 2008 </PL> ;
Căn_cứ <NĐ rel="Pursuant"> Nghị_định số 01/2008/NĐ-CP ngày 03/01/2008 </NĐ> của Chính_phủ quy_định chức_năng , nhiệm_vụ , quyền_hạn và cơ_cấu tổ_chức của Bộ Nông_nghiệp và Phát_triển nông_thôn ;
Căn_cứ <NĐ rel="Pursuant"> Nghị_định số 128/2008/NĐ-CP ngày 16/12/2008 </NĐ> của Chính_phủ quy_định chi_tiết thi_hành một_số điều của <PL rel="Others"> Pháp_lệnh Xử_lý vi_phạm hành_chính năm 2002 </PL> và <PL rel="Others"> Pháp_lệnh sửa_đổi , bổ_sung một_số điều của <PL rel="Others"> Pháp_lệnh Xử_lý vi_phạm hành_chính </PL> năm 2008 </PL> ;
Căn_cứ <NĐ rel="Pursuant"> Nghị_định số 40/2009/NĐ-CP ngày 24/4/2009 </NĐ> của Chính_phủ quy_định về xử_phạt vi_phạm hành_chính trong lĩnh_vực thú_y ;
Điều 1 .  Phạm_vi điều_chỉnh và đối_tượng áp_dụng 

1 . Phạm_vi điều_chỉnh : 

Thông_tư này hướng_dẫn chi_tiết về hình_thức , thời_hiệu , thẩm_quyền , trình_tự , thủ_tục xử_phạt vi_phạm hành_chính ( viết tắt là VPHC ) trong lĩnh_vực thú_y và một_số hành_vi VPHC trong lĩnh_vực thú_y . 

2 . Đối_tượng áp_dụng : 

Thông_tư này áp_dụng đối_với tổ_chức , cá_nhân Việt_Nam ;  tổ_chức , cá_nhân nước_ngoài có hoạt_động liên_quan đến lĩnh_vực thú_y trên lãnh_thổ Việt_Nam . 

Điều 2 .  Áp_dụng quy_định của các Nghị_định có liên_quan trong xử_phạt vi_phạm hành_chính trong lĩnh_vực thú_y 

1 . Khi xử_phạt VPHC trong lĩnh_vực thú_y , người có thẩm_quyền xử_phạt phải áp_dụng hình_thức , mức xử_phạt quy_định tại <NĐ rel="Reference"> Nghị_định số 40/2009/NĐ-CP ngày 24/4/2009 </NĐ> của Chính_phủ quy_định về xử_phạt vi_phạm hành_chính trong lĩnh_vực thú_y ( sau đây gọi là <NĐ rel="Reference"> Nghị_định số 40/2009/NĐ-CP </NĐ> ) . Trong trường_hợp hành_vi VPHC không được quy_định tại <NĐ rel="Reference"> Nghị_định số 40/2009/NĐ-CP </NĐ> thì mới áp_dụng hình_thức , mức phạt quy_định tại các Nghị_định khác của Chính_phủ về xử_phạt VPHC trong lĩnh_vực quản_lý nhà_nước có liên_quan .
2 . Việc xử_phạt các hành_vi vi_phạm_quy_định về hàng_hóa cấm kinh_doanh ; kinh_doanh hàng_hóa nhập lậu ; vi_phạm_quy_định về nhãn hàng_hóa ; kinh_doanh hàng giả ; kinh_doanh tem , nhãn , bao_bì hàng hóa giả ; kinh_doanh hàng_hóa quá hạn sử_dụng được thực_hiện theo quy_định tại các Điều 18 , 22 , 23 , 24 , 25 , 26 của <NĐ rel="Reference"> Nghị_định số 06/2008/NĐ-CP ngày 16/01/2008 </NĐ> của Chính_phủ quy_định về xử_phạt VPHC trong hoạt_động thương_mại ( sau đây gọi là <NĐ rel="Reference"> Nghị_định số 06/2008/NĐ-CP </NĐ> ) .
3 . Việc xử_phạt các hành_vi VPHC liên_quan đến đo_lường , chất_lượng sản_phẩm hàng_hóa , người có thẩm_quyền xử_phạt được áp_dụng các quy_định tại <NĐ rel="Reference"> Nghị_định số 54/2009/NĐ-CP ngày 05/6/2009 </NĐ> của Chính_phủ quy_định về xử_phạt VPHC trong lĩnh_vực tiêu_chuẩn , đo_lường và chất_lượng sản_phẩm , hàng hóa .
4 . Ngoài các Nghị_định nêu tại các khoản 2 , 3 Điều này , người có thẩm_quyền xử_phạt VPHC trong lĩnh_vực thú_y có quyền áp_dụng hình_thức , mức xử_phạt quy_định tại các Nghị_định khác của Chính_phủ về xử_phạt VPHC trong các lĩnh_vực quản_lý nhà_nước có liên_quan . 

Điều 3 .  Thời_hiệu xử_phạt vi_phạm hành_chính 

1 . Thời_hiệu xử_phạt VPHC trong lĩnh_vực thú_y là một năm , kể từ ngày VPHC được thực_hiện , tức_là ngày hành_vi VPHC được phát_hiện và người có thẩm_quyền lập biên_bản VPHC theo quy_định của pháp_luật đối_với người vi_phạm . 

2 . Các hành_vi VPHC liên_quan đến xuất_khẩu , nhập_khẩu động_vật , sản_phẩm động_vật , thuốc thú_y ;  sản_xuất , kinh_doanh thuốc thú_y giả thì thời_hiệu xử_phạt là hai năm , bao_gồm : 

a ) Hành_vi vi_phạm_quy_định về kiểm_dịch động_vật , sản_phẩm động_vật xuất_khẩu , nhập_khẩu , tạm nhập tái_xuất , tạm xuất tái_nhập , chuyển cửa_khẩu , quá_cảnh lãnh_thổ Việt_Nam được quy_định tại Điều 14 của <NĐ rel="Reference"> Nghị_định số 40/2009/NĐ-CP </NĐ> ;
Hành_vi vi_phạm_quy_định về nhập_khẩu thuốc thú_y , nguyên_liệu làm thuốc thú_y được quy_định tại Điều 20 của <NĐ rel="Reference"> Nghị_định 40/2009/NĐ-CP </NĐ> ;
Hành_vi kinh_doanh thuốc thú_y giả được quy_định tại khoản 7 Điều 24 của <NĐ rel="Reference"> Nghị_định số 06/2008/NĐ-CP </NĐ> .
Điều 4 .  Các hình_thức xử_phạt chính 

1 . Hình_thức phạt cảnh_cáo : 

a ) Hình_thức phạt cảnh_cáo chỉ được áp_dụng đối_với các hành_vi VPHC mà <NĐ rel="Reference"> Nghị_định số 40/2009/NĐ-CP </NĐ> quy_định hình_thức phạt cảnh_cáo đối_với hành_vi đó và khi có các tình_tiết_giảm nhẹ như VPHC lần đầu , có quy_mô nhỏ , không đáng_kể ; VPHC do lạc_hậu , không hiểu_biết các quy_định của pháp_luật về hành_vi vi_phạm đó .
VPHC lần đầu trong lĩnh_vực thú_y là trường_hợp tổ_chức , cá_nhân trước đó chưa bị xử_phạt VPHC trong lĩnh_vực thú_y hoặc đã bị xử_phạt VPHC trong lĩnh_vực thú_y nhưng đã quá một năm kể từ ngày chấp_hành xong quyết_định xử_phạt VPHC hoặc từ ngày hết thời_hiệu thi_hành quyết_định xử_phạt mà không tái_phạm . 

1 . Tịch_thu tang_vật , phương_tiện được sử_dụng để VPHC là hình_thức xử_phạt bổ_sung , được áp_dụng kèm theo hình_thức xử_phạt chính . Trong lĩnh_vực quản_lý nhà_nước về thú_y , các trường_hợp cụ_thể bị áp_dụng tịch_thu tang_vật , phương_tiện được quy_định tại <NĐ rel="Reference"> Nghị_định số 40/2009/NĐ-CP </NĐ> .
Trong khi thực_hiện xử_phạt VPHC , người có thẩm_quyền xử_phạt không được tùy_tiện áp_dụng hình_thức xử_phạt bổ_sung tịch_thu tang_vật , phương_tiện được sử_dụng để thực_hiện VPHC nếu Nghị_định của Chính_phủ không quy_định . 

2 . Tước quyền sử_dụng giấy_phép , chứng_chỉ hành_nghề trong lĩnh_vực thú_y là hình_thức xử_phạt bổ_sung , được áp_dụng kèm theo hình_thức xử_phạt chính trong trường_hợp cá_nhân , tổ_chức vi_phạm nghiêm_trọng quy_định sử_dụng giấy_phép , chứng_chỉ hành_nghề . 

Tước quyền sử_dụng giấy_phép , chứng_chỉ hành_nghề được áp_dụng có thời_hạn hoặc không có thời_hạn và được quy_định đối_với hành_vi VPHC cụ_thể , tùy thuộc vào tính_chất , mức_độ của hành_vi vi_phạm đó . 

3 . Ngoài các hình_thức xử_phạt chính , hình_thức phạt bổ_sung đã nêu trên , tổ_chức , cá_nhân VPHC còn có_thể bị áp_dụng một hoặc nhiều biện_pháp khắc_phục hậu_quả được quy_định tại khoản 3 Điều 7 <NĐ rel="Reference"> Nghị_định số 40/2009/NĐ-CP </NĐ> .
Các biện_pháp khắc_phục hậu_quả phải áp_dụng kèm theo hình_thức phạt chính , trừ trường_hợp người có thẩm_quyền xử_phạt VPHC để quá thời_hạn ra quyết_định xử_phạt theo quy_định tại Điều 56 của <PL rel="Reference"> Pháp_lệnh Xử_lý VPHC năm 2002 </PL> . Trong trường_hợp không ra quyết_định xử_phạt thì người có thẩm_quyền xử_phạt vẫn có_thể áp_dụng các biện_pháp khắc_phục hậu_quả quy_định tại khoản 3 Điều 7 <NĐ rel="Reference"> Nghị_định số 40/2009/NĐ-CP </NĐ> đối_với người VPHC .
Tổ_chức , cá_nhân vi_phạm phải chịu mọi chi_phí để thực_hiện các biện_pháp khắc_phục hậu_quả . 

Điều 6 .  Hành_vi vi_phạm_quy_định về phòng_bệnh , chữa bệnh , chống dịch_bệnh cho động_vật 

1 . Vi_phạm_quy_định về phòng_bệnh , chữa bệnh cho động_vật trên cạn : 

a ) Hành_vi vi_phạm_quy_định tại điểm c khoản 2 Điều 9 của <NĐ rel="Reference"> Nghị_định số 40/2009/NĐ-CP </NĐ> được hiểu là hành_vi không tuân_thủ các quy_định về điều_kiện vệ_sinh thú_y , khai_báo dịch_bệnh , tiêm phòng , kiểm_dịch động_vật , chẩn_đoán bệnh quy_định tại bản Quy_định vùng , cơ_sở an_toàn dịch_bệnh động_vật được ban_hành kèm theo <QĐ rel="Reference"> Quyết_định số 66/2008/QĐ-BNN ngày 26/5/2008 </QĐ> của Bộ_trưởng Bộ Nông_nghiệp và Phát_triển nông_thôn .
b ) Hành_vi vi_phạm_quy_định tại khoản 6 Điều 9 của <NĐ rel="Reference"> Nghị_định số 40/2009/NĐ-CP </NĐ> được hiểu là hành_vi vứt , bỏ động_vật bị mắc bệnh , bị chết vì bệnh ra môi_trường , ao , hồ , kênh , rạch , sông , ngòi hay các nguồn nước tự_nhiên khác mà không thực_hiện tiêu_hủy theo đúng quy_định . Việc xác_định động_vật bị mắc bệnh , bị chết vì bệnh truyền_nhiễm nguy_hiểm được căn_cứ vào kết_quả chẩn_đoán lâm_sàng của nhân_viên thú_y , cơ_quan thú_y có thẩm_quyền được tiến_hành tại địa_điểm VPHC mà không cần có kết_quả xét_nghiệm phi lâm_sàng .
2 . Vi_phạm_quy_định về chống dịch_bệnh cho động_vật trên cạn : 

a ) Hành_vi vi_phạm_quy_định tại điểm b khoản 2 Điều 10 của <NĐ rel="Reference"> Nghị_định số 40/2009/NĐ-CP </NĐ> được hiểu là hành_vi sử_dụng phương_tiện vận_chuyển không đạt tiêu_chuẩn vệ_sinh thú_y để vận_chuyển_động_vật đi giết_mổ bắt_buộc , có khả_năng làm rơi , vãi thức_ăn , chất_thải của động_vật trên đường đi hoặc vận_chuyển_động_vật mắc bệnh_dịch từ phương_tiện vận_chuyển đã được cơ_quan thú_y có thẩm_quyền kiểm_tra , chấp_thuận sang phương_tiện chưa được kiểm_tra , vệ_sinh , tiêu độc hoặc tự_ý dừng đỗ phương_tiện vận_chuyển không đúng nơi quy_định , để động_vật mắc bệnh tiếp_xúc với động vật_khỏe mạnh khác trên đường đến nơi giết_mổ được chỉ_định .
b ) Hành_vi vi_phạm_quy_định tại điểm đ khoản 3 Điều 10 của <NĐ rel="Reference"> Nghị_định số 40/2009/NĐ-CP </NĐ> được hiểu là hành_vi sử_dụng xe không phải là xe chuyên_dụng để vận_chuyển_động_vật hoặc sử_dụng xe chuyên_dụng nhưng không đạt tiêu_chuẩn vệ_sinh thú_y theo quy_định hoặc không thực_hiện vệ_sinh , khử_trùng , tiêu độc phương_tiện sau vận_chuyển_động_vật hoặc nơi giết_mổ không đảm_bảo các điều_kiện vệ_sinh thú_y , không thực_hiện vệ_sinh , khử_trùng tiêu độc sau giết_mổ theo hướng_dẫn của cơ_quan thú_y .
c ) Hành_vi vi_phạm_quy_định tại điểm e khoản 3 Điều 10 của <NĐ rel="Reference"> Nghị_định số 40/2009/NĐ-CP </NĐ> bao_gồm các hành_vi sau đây :
Giết_mổ , xử_lý động_vật , xác động_vật mắc bệnh hoặc nghi mắc bệnh , sản_phẩm động_vật_mang mầm bệnh thuộc Danh_mục bệnh phải công_bố dịch không đúng địa_điểm được chỉ_định , không theo đúng quy_định ; 

Không chôn , đốt động_vật mắc bệnh , nghi mắc bệnh ;  xác động_vật chết vì bệnh mà theo quy_định phải tiêu_hủy hoặc chôn không đúng độ sâu , không đúng kỹ_thuật , nơi chôn gần các nguồn nước tự_nhiên , nước sinh_hoạt ; 

Không xử_lý nơi chôn , đốt động_vật theo đúng hướng_dẫn của cơ_quan thú_y có thẩm_quyền . 

Điều 7 .  Hành_vi vi_phạm_quy_định về kiểm_dịch động_vật , sản_phẩm động_vật , kiểm_soát giết_mổ , kiểm_tra vệ_sinh thú_y 

1 . Vi_phạm_quy_định về kiểm_dịch động_vật , sản_phẩm động_vật trên cạn lưu_thông trong nước : 

Hành_vi vi_phạm_quy_định tại điểm a khoản 2 Điều 12 của <NĐ rel="Reference"> Nghị_định số 40/2009/NĐ-CP </NĐ> là hành_vi vận_chuyển , kinh_doanh động_vật , sản_phẩm động_vật thuộc Danh_mục đối_tượng kiểm_dịch động_vật , sản_phẩm động_vật nhưng chủ hàng hoặc người điều_khiển phương_tiện vận_chuyển không xuất_trình được Giấy chứng_nhận kiểm_dịch động_vật , sản_phẩm động_vật do cơ_quan thú_y có thẩm_quyền cấp .
Trong trường_hợp hành_vi vi_phạm này xảy ra tại thời_điểm có bất_kỳ một huyện , quận , thị_xã , thành_phố thuộc tỉnh trong phạm_vi cả nước đang công_bố có dịch_bệnh trên loài động_vật đó thì người có thẩm_quyền xử_phạt VPHC phải áp_dụng biện_pháp khắc_phục hậu_quả buộc tiêu_hủy động_vật , sản_phẩm động_vật nếu chủ hàng không chứng_minh được nguồn_gốc của động_vật , sản_phẩm động_vật , cụ_thể là không xuất_trình được giấy xác_nhận của Ủy_ban nhân_dân xã về nguồn_gốc động_vật , sản_phẩm động_vật . 

2 . Hành_vi vi_phạm_quy_định tại điểm b khoản 1 Điều 13 của <NĐ rel="Reference"> Nghị_định số 40/2009/NĐ-CP </NĐ> là hành_vi vận_chuyển con_giống thủy_sản ra khỏi cơ_sở sản_xuất , kinh_doanh con_giống mà không được cơ_quan thú_y có thẩm_quyền kiểm_dịch và cấp giấy chứng_nhận kiểm_dịch . Trong trường_hợp con_giống thủy_sản đã được kiểm_dịch thì chủ hàng khi bán con_giống phải cung_cấp bản photo giấy chứng_nhận kiểm_dịch do cơ_quan thú_y có thẩm_quyền cấp cho người mua .
3 . Vi_phạm_quy_định về kiểm_dịch động_vật , sản_phẩm động_vật xuất_khẩu , nhập_khẩu , tạm xuất tái_nhập , tạm nhập tái_xuất , chuyển cửa_khẩu , quá_cảnh lãnh_thổ Việt_Nam . 

a ) Hành_vi vi_phạm_quy_định tại điểm a khoản 1 Điều 14 của <NĐ rel="Reference"> Nghị_định số 40/2009/NĐ-CP </NĐ> là hành_vi cá_nhân mang theo người , hành_lý các loại động_vật , sản_phẩm động_vật với khối_lượng , số_lượng vượt quá khối_lượng , số_lượng cho phép ; sản_phẩm có nguồn_gốc từ động_vật mà chưa qua chế_biến công_nghiệp ; động_vật , sản_phẩm động_vật thuộc loại luật_pháp quốc_tế cấm lưu_thông , vận_chuyển hoặc không xuất_trình được giấy chứng_nhận kiểm_dịch hợp_lệ do cơ_quan thú_y quốc_gia nước xuất_khẩu cấp .
b ) Hành_vi vi_phạm_quy_định tại khoản 2 Điều 14 của <NĐ rel="Reference"> Nghị_định số 40/2009/NĐ-CP </NĐ> là hành_vi không xuất_trình được với cơ_quan kiểm_dịch động_vật cửa_khẩu bộ hồ_sơ kiểm_dịch hợp_lệ đối_với lô hàng_hóa đó .
Một bộ hồ_sơ kiểm_dịch không hợp_lệ có_thể là : 

Thiếu giấy chứng_nhận kiểm_dịch hoặc có giấy chứng_nhận kiểm_dịch nhưng thiếu chữ_ký ;  có giấy chứng_nhận kiểm_dịch nhưng nội_dung không đúng với thực_tế về loài , số_lượng động_vật hoặc các thông_tin về sản_phẩm động_vật như ngày sản_xuất , hạn sử_dụng … ;  nội_dung bị tẩy xóa , sửa_chữa ;  sử_dụng giấy chứng_nhận kiểm_dịch không do cơ_quan thú_y có thẩm_quyền cấp ;  thiếu một trong các giấy_tờ khác có liên_quan đến việc xuất_khẩu , nhập_khẩu , tạm nhập tái_xuất , tạm xuất tái_nhập , chuyển cửa_khẩu quá_cảnh lãnh_thổ Việt_Nam đối_với lô hàng_hóa đó . 

c ) Hành_vi vi_phạm_quy_định tại điểm e khoản 3 Điều 14 của <NĐ rel="Reference"> Nghị_định số 40/2009/NĐ-CP </NĐ> là các hành_vi :
Để động_vật đang trong thời_gian cách_ly kiểm_dịch tiếp_xúc với các động_vật nội_địa khác ; 

Xuất_bán , sử_dụng làm giống động_vật , sản_phẩm động_vật chưa hết thời_gian cách_ly kiểm_dịch ; 

Không tiêm phòng các bệnh thuộc Danh_mục các bệnh phải tiêm phòng đối_với động_vật trong thời_gian cách_ly kiểm_dịch ; 

Không chấp_hành việc lấy mẫu xét_nghiệm bệnh của cơ_quan thú_y có thẩm_quyền ; 

Không đảm_bảo các yêu_cầu về vệ_sinh thú_y trong thời_gian cách_ly kiểm_dịch . 

d ) Hành_vi vi_phạm_quy_định tại khoản 8 Điều 14 của <NĐ rel="Reference"> Nghị_định số 40/2009/NĐ-CP </NĐ> là hành_vi của tổ_chức , cá_nhân đưa vào lãnh_thổ của Việt_Nam khi chưa có văn_bản đồng_ý của Cục Thú_y và không thực_hiện kiểm_dịch đối_với các loại hàng_hóa , vật_phẩm sau :
Các loại bệnh_phẩm để phục_vụ cho công_tác xét_nghiệm , chẩn_đoán bệnh hoặc sử_dụng cho các mục_đích khác ; 

Các đối_tượng thuộc Danh_mục đối_tượng kiểm_dịch , bao_gồm vi_sinh_vật , ký_sinh_trùng gây bệnh động_vật , vi_sinh_vật gây ô_nhiễm , các hóa chất độc_hại , các đối_tượng khác được quy_định tại <QĐ rel="Reference"> Quyết_định số 45/2005/QĐ-BNN ngày 25/7/2005 </QĐ> của Bộ_trưởng Bộ Nông_nghiệp và Phát_triển Nông_thôn .
e ) Hành_vi giết_mổ động_vật , sơ_chế sản_phẩm động_vật không rõ nguồn_gốc xuất_xứ quy_định tại điểm đ khoản 2 Điều 15 của <NĐ rel="Reference"> Nghị_định số 40/2009/NĐ-CP </NĐ> là hành_vi giết_mổ động_vật không có giấy chứng_nhận kiểm_dịch hoặc không có giấy xác_nhận nguồn_gốc của thú_y xã hoặc không có giấy chứng_nhận tiêm phòng của cơ_quan thú_y ở địa_phương ; sơ_chế sản_phẩm động_vật không có giấy chứng_nhận kiểm_dịch nhập_khẩu hoặc không có tem vệ_sinh thú_y của cơ_quan thú_y , cơ_quan kiểm_dịch có thẩm_quyền .
g ) Hành_vi vi_phạm_quy_định tại khoản 5 Điều 16 của <NĐ rel="Reference"> Nghị_định số 40/2009/NĐ-CP </NĐ> là hành_vi của tổ_chức , cá_nhân kinh_doanh động_vật thủy_sản , sản_phẩm động_vật tươi_sống mà kết_quả kiểm_tra của cơ_quan thú_y có thẩm_quyền cho thấy bị nhiễm_khuẩn hoặc có chất tồn_dư vượt quá giới_hạn cho phép .
Tùy từng trường_hợp , người có thẩm_quyền xử_phạt có_thể cho phép chuyển mục_đích sử_dụng như làm thức_ăn chăn_nuôi đối_với động_vật thủy_sản , sản_phẩm động_vật tươi_sống bị nhiễm_khuẩn hoặc có chất tồn_dư quá giới_hạn cho phép .  Việc xử_lý đối_với sản_phẩm động_vật không đạt tiêu_chuẩn vệ_sinh thực_phẩm phải theo hướng_dẫn của Bộ Nông_nghiệp và Phát_triển nông_thôn . 

Điều 8 .  Hành_vi vi_phạm_quy_định về quản_lý thuốc thú_y , chế_phẩm sinh_học , vi_sinh_vật , hóa_chất dùng trong thú_y , thú_y thủy_sản ( sau đây gọi chung là thuốc thú_y ) 

1 . Hành_vi vi_phạm_quy_định tại khoản 2 Điều 18 của <NĐ rel="Reference"> Nghị_định số 40/2009/NĐ-CP </NĐ> là hành_vi sản_xuất một lô thuốc thú_y có chỉ_tiêu về lý , hóa , vi_sinh , hàm ẩm không đạt hoặc một hoặc nhiều thành_phần của thuốc có hàm_lượng thực_tế thấp hơn hoặc vượt quá sai_số cho phép về hàm_lượng mà cơ_sở đã đăng_ký với cơ_quan thú_y có thẩm_quyền khi đăng_ký lưu_hành hoặc tự công_bố theo quy_định của <L rel="Reference"> Luật Chất_lượng sản_phẩm hàng_hóa </L> .
2 . Hành_vi vi_phạm_quy_định tại điểm b khoản 4 Điều 19 của <NĐ rel="Reference"> Nghị_định số 40/2009/NĐ-CP </NĐ> là hành_vi kinh_doanh một loại thuốc thú_y có chỉ_tiêu về lý , hóa , vi_sinh , hàm ẩm không đạt hoặc có một hoặc nhiều hoạt_chất có hàm_lượng thực_tế thấp hơn hoặc vượt quá mức sai_số cho phép mà cơ_sở sản_xuất đã đăng_ký với cơ_quan thú_y có thẩm_quyền khi đăng_ký lưu_hành sản_phẩm hoặc công_bố trên nhãn thuốc .
3 . Hành_vi vi_phạm_quy_định tại khoản 3 Điều 20 của <NĐ rel="Reference"> Nghị_định số 40/2009/NĐ-CP </NĐ> là hành_vi tổ_chức , cá_nhân nhập_khẩu một lô thuốc , nguyên_liệu làm thuốc thú_y có chỉ_tiêu về lý , hóa , vi_sinh , hàm ẩm không đạt hoặc một hoặc nhiều thành_phần của thuốc có hàm_lượng thực_tế thấp hơn hoặc vượt quá sai_số cho phép về hàm_lượng mà cơ_sở đã đăng_ký với cơ_quan thú_y có thẩm_quyền khi đăng_ký lưu_hành sản_phẩm hoặc công_bố trên nhãn thuốc .
4 . Hành_vi vi_phạm_quy_định tại điểm a khoản 1 Điều 21 của <NĐ rel="Reference"> Nghị_định số 40/2009/NĐ-CP </NĐ> là hành_vi của tổ_chức , cá_nhân thông_tin , quảng_cáo trên nhãn thuốc , trên các phương_tiện truyền_thông , thông_tin đại_chúng như báo_chí , đài phát_thanh_truyền_hình Trung_ương hoặc địa_phương , pa no quảng_cáo , tờ_rơi , tờ bướm . . với những nội_dung không đúng về thành_phần , công_dụng , công_hiệu , chức_năng hoặc về chất_lượng của thuốc đã đăng_ký .
5 . Hành_vi vi_phạm_quy_định tại khoản 2 Điều 23 của <NĐ rel="Reference"> Nghị_định số 40/2009/NĐ-CP </NĐ> là hành_vi sản_xuất , nhập_khẩu thuốc thú_y thuộc loại hàng_hóa phải công_bố chất_lượng hợp chuẩn , hợp quy theo quy_định của pháp_luật về tiêu_chuẩn và quy_chuẩn kỹ_thuật nhưng cơ_sở sản_xuất , nhập_khẩu chưa thực_hiện công_bố hợp chuẩn , hợp quy hoặc thuốc thú_y không phù_hợp với tiêu_chuẩn công_bố áp_dụng , quy_chuẩn kỹ_thuật tương_ứng mà đã tự_ý sử_dụng tem hợp chuẩn , hợp quy trên sản_phẩm hoặc thông_tin , quảng_cáo trên các phương_tiện thông_tin đại_chúng , báo_chí , đài phát_thanh_truyền_hình , tờ_rơi , tờ bướm . . là đã công_bố hợp chuẩn , hợp quy .
Điều 9 .  Hành_vi vi_phạm các quy_định khác trong lĩnh_vực thú_y 

1 . Hành_vi vi_phạm_quy_định tại điểm a khoản 1 , điểm a khoản 6 , điểm a khoản 8 Điều 24 của <NĐ rel="Reference"> Nghị_định số 40/2009/NĐ-CP </NĐ> là hành_vi của người được cấp chứng_chỉ hành_nghề có các hoạt_động hành_nghề thú_y khác với lĩnh_vực chuyên_môn đã được quy_định trong chứng_chỉ hành_nghề do cơ_quan thú_y có thẩm_quyền cấp .
2 . Hành_vi vi_phạm_quy_định tại điểm b khoản 5 , điểm a khoản 7 , điểm a khoản 9 Điều 24 của <NĐ rel="Reference"> Nghị_định số 40/2009/NĐ-CP </NĐ> là hành_vi tự_ý thêm vào , xóa_bỏ , làm thay_đổi nội_dung ban_đầu của chứng_chỉ hành_nghề do cơ_quan thú_y có thẩm_quyền cấp .
3 . Hành_vi vi_phạm_quy_định tại điểm c khoản 5 , điểm c khoản 7 , điểm b khoản 9 Điều 24 của <NĐ rel="Reference"> Nghị_định số 40/2009/NĐ-CP </NĐ> là hành_vi kê_khai , khai_báo gian_dối , không_trung_thực các thông_tin về bằng_cấp chuyên_môn , trình_độ chuyên_môn , cung_cấp bản_sao các loại giấy chứng_nhận , văn_bằng không phải là bản_sao do cơ_quan có thẩm_quyền cấp , chứng_thực để được cấp mới hoặc cấp gia_hạn chứng_chỉ hành_nghề thú_y .
4 . Hành_vi vi_phạm_quy_định tại điểm d khoản 5 , điểm d khoản 7 , điểm d khoản 9 Điều 24 của <NĐ rel="Reference"> Nghị_định số 40/2009/NĐ-CP </NĐ> là hành_vi của cá_nhân sử_dụng chứng_chỉ hành_nghề không phải do cơ_quan thú_y có thẩm_quyền cấp để hành_nghề .
Điều 10 .  Thẩm_quyền xử_phạt vi_phạm hành_chính 

1 . Nguyên_tắc xác_định thẩm_quyền xử_phạt VPHC được thực_hiện theo quy_định tại Điều 42 của <PL rel="Reference"> Pháp_lệnh Xử_lý VPHC </PL> , Điều 15 của <NĐ rel="Reference"> Nghị_định số 128/2008/NĐ-CP ngày 16/12/2008 </NĐ> của Chính_phủ ( sau đây gọi tắt là <NĐ rel="Reference"> Nghị_định 128/2008/NĐ-CP </NĐ> ) Quy_định chi_tiết thi_hành một_số điều của <PL rel="Others"> Pháp_lệnh Xử_lý VPHC năm 2002 </PL> và <PL rel="Others"> Pháp_lệnh sửa_đổi bổ_sung một_số điều của <PL rel="Others"> Pháp_lệnh Xử_lý VPHC </PL> năm 2008 </PL> và quy_định tại các Điều 29 , 30 , 31 của <NĐ rel="Others"> Nghị_định số 40/2009/NĐ-CP </NĐ> .
2 . Trong trường_hợp xử_phạt một người thực_hiện nhiều hành_vi VPHC trong lĩnh_vực thú_y thì thẩm_quyền xử_phạt được xác_định như sau : 

a ) Nếu hình_thức , mức xử_phạt được quy_định đối_với từng hành_vi đều thuộc thẩm_quyền của chức_danh được quy_định tại các khoản 1 , 2 , 3 , 4 , 5 Điều 29 <NĐ rel="Reference"> Nghị_định 40/2009/NĐ-CP </NĐ> thì thẩm_quyền xử_phạt vẫn thuộc chức_danh đó .
b ) Trong trường_hợp mức tiền phạt , trị_giá tang_vật phương_tiện bị tịch_thu hoặc một trong các hình_thức xử_phạt hoặc biện_pháp khắc_phục hậu_quả không thuộc thẩm_quyền hoặc vượt quá thẩm_quyền của mình thì người đang thụ_lý vụ_việc vi_phạm phải kịp_thời chuyển vụ_việc đó đến người có thẩm_quyền xử_phạt . 

3 . Chánh thanh_tra Chi_cục Thú_y cấp tỉnh , Chánh thanh_tra Cục Thú_y có thẩm_quyền xử_phạt VPHC đối_với những hành_vi vi_phạm được phát_hiện trong khi thi_hành công_vụ và xử_lý các vụ VPHC do thanh_tra viên chuyên_ngành thú_y hoặc cán_bộ thú_y chuyển hồ_sơ theo quy_định của pháp_luật . 

4 . Khi áp_dụng hình_thức tước quyền sử_dụng chứng_chỉ hành_nghề thú_y , người có thẩm_quyền xử_phạt VPHC thu_giữ giấy_phép , chứng_chỉ hành_nghề và ghi rõ trong quyết_định xử_phạt .  Trong thời_hạn 03 ( ba ) ngày , kể từ ngày ban_hành quyết_định xử_phạt VPHC , người có thẩm_quyền xử_phạt thông_báo với cơ_quan đã cấp giấy_phép , chứng_chỉ hành_nghề về việc áp_dụng hình_thức xử_phạt tước quyền sử_dụng giấy_phép , chứng_chỉ hành_nghề đối_với cá_nhân vi_phạm . 

5 . Khi áp_dụng hình_thức tịch_thu tang_vật , phương_tiện VPHC , thanh_tra viên chuyên_ngành thú_y đang thi_hành công_vụ có thẩm_quyền tịch_thu tang_vật , phương_tiện được sử_dụng để VPHC có giá_trị đến 2.000.000 đồng theo quy_định tại điểm b , khoản 1 Điều 29 của <NĐ rel="Reference"> Nghị_định 40/2009/NĐ-CP </NĐ> . Trị_giá của tang_vật , phương_tiện VPHC được xác_định dựa trên giá_trị thực_tế của tang_vật , phương_tiện tại thời_điểm , nơi xảy ra VPHC .
Điều 11 .  Biện_pháp tạm giữ tang_vật , phương_tiện nhằm ngăn_chặn vi_phạm hành_chính : 

1 . Thẩm_quyền tạm giữ tang_vật , phương_tiện VPHC : 

a ) Những người có thẩm_quyền tạm giữ tang_vật , phương_tiện VPHC trong lĩnh_vực thú_y bao_gồm các chức_danh được quy_định tại Điều 46 của <PL rel="Reference"> Pháp_lệnh Xử_lý VPHC </PL> .
b ) Thanh_tra viên chuyên_ngành thú_y đang thi_hành công_vụ được quyền ra quyết_định tạm giữ tang_vật , phương_tiện VPHC trong trường_hợp có căn_cứ cho rằng nếu không tạm giữ tang_vật , phương_tiện VPHC ngay thì tang_vật , phương_tiện VPHC có_thể bị tẩu_tán , tiêu_hủy .  Trong thời_hạn 24 giờ , kể từ khi ra quyết_định tạm giữ , người ra quyết_định tạm giữ phải báo_cáo cho thủ_trưởng trực_tiếp của mình là một trong những người có thẩm_quyền tạm giữ tang_vật , phương_tiện VPHC quy_định tại điểm a khoản 1 Điều này và được sự đồng_ý bằng văn_bản của người đó .  Trong trường_hợp không được sự đồng_ý của các chức_danh quy_định tại điểm a , khoản 1 Điều này thì người ra quyết_định tạm giữ phải hủy ngay quyết_định tạm giữ và trả lại tang_vật , phương_tiện đã bị tạm giữ .  Khi trả lại tang_vật , phương_tiện VPHC , người có thẩm_quyền phải ra quyết_định theo mẫu tại Phụ_lục IV kèm theo Thông_tư này . 

2 . Chỉ tạm giữ tang_vật , phương_tiện VPHC khi thấy thật cần_thiết để ngăn_chặn ngay hành_vi vi_phạm hoặc để phòng_ngừa hậu_quả xấu có_thể xảy ra đối_với con_người và động_vật , cụ_thể : 

a ) Tang_vật VPHC là động_vật , sản_phẩm động_vật nghi mắc bệnh , mang mầm bệnh ;  động_vật , sản_phẩm động_vật không rõ nguồn_gốc , xuất_xứ hoặc sản_phẩm động_vật nghi_ngờ không đạt tiêu_chuẩn vệ_sinh thú_y ;  thuốc thú_y , nguyên_liệu làm thuốc thú_y , chế_phẩm sinh_học , vi_sinh_vật , hóa_chất dùng trong thú_y thuộc Danh_mục thuốc thú_y cấm lưu_hành tại Việt_Nam , thuốc thú_y nghi_ngờ được làm giả , làm nhái nhãn_mác , hết hạn sử_dụng , không có trong Danh_mục thuốc thú_y được phép lưu_hành tại Việt_Nam ;  các trường_hợp cụ_thể khác do người có thẩm_quyền xử_lý VPHC quyết_định . 

b ) Việc áp_dụng biện_pháp tạm giữ tang_vật , phương_tiện VPHC phải tuân_thủ đúng trình_tự , thủ_tục quy_định .  Trường_hợp không tuân_thủ các quy_định , gây ra thiệt_hại về vật_chất cho người vận_chuyển hàng_hóa , chủ hàng_hóa thì cán_bộ , công_chức gây ra thiệt_hại phải chịu trách_nhiệm bồi_thường về vật_chất cho người bị thiệt_hại . 

3 . Trình_tự thủ_tục tạm giữ tang_vật , phương_tiện VPHC : 

a ) Trên_cơ_sở quyết_định tạm giữ tang_vật , phương_tiện VPHC , người đã ra quyết_định phải lập Biên_bản tạm giữ tang_vật , phương_tiện VPHC . Trong biên_bản phải ghi đầy_đủ các nội_dung theo quy_định và giao cho người vi_phạm một bản . Nếu người vi_phạm không ký vào biên_bản thì phải ghi rõ lý_do . Biên_bản phải theo đúng mẫu tại Phụ_lục số II ban_hành kèm theo <NĐ rel="Reference"> Nghị_định số 40/2009/NĐ-CP </NĐ> .
b ) Người ra quyết_định tạm giữ tang_vật , phương_tiện VPHC có trách_nhiệm phối_hợp với chính_quyền địa_phương hoặc cơ_quan có thẩm_quyền nơi xảy ra vi_phạm bố_trí nơi tạm giữ , bảo_quản tang_vật , phương_tiện VPHC bị tạm giữ .  Trường_hợp không bố_trí được nơi tạm giữ hoặc không_thể di_chuyển tang_vật , phương_tiện VPHC về nơi tạm giữ thì người ra quyết_định tạm giữ phải áp_dụng các biện_pháp để tránh việc người vi_phạm tẩu_tán tang_vật , phương_tiện VPHC và có_thể yêu_cầu chủ phương_tiện tự bảo_quản , trông_coi phương_tiện VPHC và tang_vật VPHC được chuyên_chở , vận_chuyển trên phương_tiện đó . 

c ) Trong thời_hạn 10 ngày , kể từ ngày tạm giữ tang_vật , phương_tiện VPHC , người ra quyết_định tạm giữ phải xử_lý tang_vật , phương_tiện VPHC theo đúng các biện_pháp được ghi trong quyết_định xử_lý .  Trong trường_hợp không áp_dụng biện_pháp tịch_thu tang_vật , phương_tiện VPHC thì phải trả lại cho người vi_phạm , chủ sở_hữu tang_vật , phương_tiện VPHC . 

4 . Việc xử_lý đối_với tang_vật , phương_tiện VPHC hết thời_hạn bị tạm giữ được thực_hiện theo quy_định tại <NĐ rel="Reference"> Nghị_định 70/2006/NĐ-CP ngày 24/7/2006 </NĐ> quy_định việc quản_lý tang_vật , phương_tiện bị tạm giữ theo thủ_tục hành_chính và <NĐ rel="Reference"> Nghị_định số 22/2009/NĐ-CP ngày 24/02/2009 </NĐ> sửa_đổi , bổ_sung một_số điều <NĐ rel="Others"> Nghị_định số 70/2006/NĐ-CP ngày 24/7/2006 </NĐ> quy_định việc quản_lý tang_vật , phương_tiện bị tạm giữ theo thủ_tục hành_chính .
Điều 12 .  Trình_tự và thủ_tục xử_phạt vi_phạm hành_chính 

1 . Việc xử_phạt VPHC trong lĩnh_vực thú_y phải tuân theo trình_tự , thủ_tục được quy_định tại <PL rel="Reference"> Pháp_lệnh Xử_lý VPHC </PL> , <NĐ rel="Reference"> Nghị_định số 128/2008/NĐ-CP </NĐ> :
a ) Khi phát_hiện_hành_vi VPHC trong lĩnh_vực thú_y , người có thẩm_quyền đang thi_hành công_vụ phải đình_chỉ ngay hành_vi vi_phạm .  Việc đình_chỉ hành_vi vi_phạm trong lĩnh_vực thú_y được thể_hiện bằng biên_bản VPHC .  Trong thời_hạn 10 ngày , kể từ ngày lập biên_bản VPHC , người có thẩm_quyền xử_phạt phải ra quyết_định xử_phạt ;  đối_với vụ VPHC có nhiều tình_tiết phức_tạp thì thời_hạn ra quyết_định xử_phạt là trong vòng 30 ngày . 

b ) Người có thẩm_quyền xử_phạt VPHC áp_dụng tình_tiết tăng nặng khi ra quyết_định xử_phạt trong các trường_hợp sau đây : 

Vi_phạm nhiều lần : tổ_chức , cá_nhân thực_hiện_hành_vi VPHC trong lĩnh_vực thú_y nhưng trước đó vi_phạm này chưa bị phát_hiện , chưa bị xử_phạt hoặc chưa hết thời_hiệu xử_phạt thì được coi là vi_phạm nhiều lần trong lĩnh_vực thú_y . 

Tái_phạm : tổ_chức , cá_nhân đã bị xử_phạt về một hành_vi vi_phạm trong lĩnh_vực thú_y , nhưng chưa hết một năm , kể từ ngày chấp_hành xong quyết_định xử_phạt hoặc kể từ ngày hết thời_hiệu thi_hành quyết_định xử_phạt mà_lại tiếp_tục thực_hiện_hành_vi vi_phạm trong lĩnh_vực thú_y thì áp_dụng tình_tiết tăng nặng là tái_phạm khi ra quyết_định xử_phạt . 

c ) Đối_với hành_vi VPHC trong lĩnh_vực thú_y có hình_thức phạt chính là cảnh_cáo hoặc phạt tiền đến 200.000 đồng thì sau khi đình_chỉ hành_vi vi_phạm thì người có thẩm_quyền xử_phạt VPHC có_thể xử_phạt theo thủ_tục đơn_giản và ra quyết_định xử_phạt tại_chỗ theo mẫu quy_định tại Phụ_lục số V , ban_hành kèm theo <NĐ rel="Reference"> Nghị_định số 40/2009/NĐ-CP </NĐ> .
d ) Trường_hợp người ra quyết_định xử_phạt VPHC là thanh_tra viên chuyên_ngành thú_y , không có quyền sử_dụng con_dấu trực_tiếp thì quyết_định xử_phạt phải được đóng_dấu của Chi_cục Thú_y .  Dấu được đóng vào góc trên cùng , bên trái tại vị_trí ghi tên cơ_quan ra quyết_định xử_phạt VPHC , số và ký_hiệu của quyết_định xử_phạt . 

đ ) Trường_hợp phạt tiền đến 200.000 đồng thì người vi_phạm có_thể nộp tiền tại_chỗ cho người ra quyết_định xử_phạt và được nhận biên_lai thu tiền phạt do Bộ Tài_chính phát_hành , hoặc nộp tiền tại Kho_bạc nhà_nước được ghi trong quyết_định xử_phạt . 

Trước khi hết ngày làm_việc , người ra quyết_định xử_phạt phải bàn_giao hồ_sơ vụ VPHC , biên_lai thu tiền phạt VPHC và số tiền phạt cho người có trách_nhiệm trong đơn_vị để lưu hồ_sơ xử_phạt VPHC , nộp lại tiền phạt cho Kho_bạc Nhà_nước . 

e ) Đối_với hành_vi vi_phạm có mức phạt tiền trên 200.000 đồng thì người có thẩm_quyền đang thi_hành công_vụ phải lập biên_bản VPHC theo đúng mẫu quy_định . 

g ) Trường_hợp mức tiền phạt từ 10.000.000 đồng trở lên đối_với người vi_phạm đang gặp hoàn_cảnh khó_khăn đặc_biệt về kinh_tế , đồng_thời người vi_phạm có đơn đề_nghị được nộp tiền phạt nhiều lần ; đơn đề_nghị đã được Ủy_ban nhân_dân cấp xã nơi người vi_phạm cư_trú xác_nhận hoàn_cảnh thì người ra quyết_định xử_phạt hành_chính quyết_định bằng văn_bản cho phép người vi_phạm được nộp tiền phạt nhiều lần theo trình_tự , thủ_tục quy_định tại Điều 27 của <NĐ rel="Reference"> Nghị_định số 128/2008/NĐ-CP </NĐ> .
Quyết_định xử_phạt bằng hình_thức phạt cảnh_cáo , bằng hình_thức phạt tiền theo thủ_tục đơn_giản , biên_bản VPHC , quyết_định xử_phạt VPHC phải đảm_bảo ghi đầy_đủ các nội_dung theo các mẫu Phụ_lục được ban_hành kèm theo <NĐ rel="Reference"> Nghị_định 40/2009/NĐ-CP </NĐ> . Quyết_định xử_phạt VPHC có hiệu_lực kể từ ngày ký ban_hành , trừ trường_hợp Quyết_định có ghi ngày có hiệu_lực khác . Trong thời_hạn 10 ngày , kể từ ngày được giao quyết_định xử_phạt , cá_nhân , tổ_chức bị xử_phạt phải chấp_hành quyết_định xử_phạt .
2 . Hình_thức xử_phạt bổ_sung và biện_pháp khắc_phục hậu_quả : 

Đối_với một_số hành_vi VPHC được quy_định tại <NĐ rel="Reference"> Nghị_định 40/2009/NĐ-CP </NĐ> , ngoài hình_thức xử_phạt chính còn bị áp_dụng hình_thức xử_phạt bổ_sung và biện_pháp khắc_phục hậu_quả .
a ) Hình_thức xử_phạt bổ_sung tước quyền sử_dụng giấy_phép , chứng_chỉ hành_nghề thú_y : 

Giấy_phép là một loại giấy_tờ do cơ_quan thú_y có thẩm_quyền cấp cho tổ_chức , cá_nhân để tổ_chức , cá_nhân này được phép hoạt_động , kinh_doanh trong lĩnh_vực thú_y . 

Chứng_chỉ hành_nghề thú_y là một loại giấy_tờ do cơ_quan thú_y có thẩm_quyền cấp cho cá_nhân để cho phép cá_nhân hành_nghề về thú_y trong một lĩnh_vực nhất_định . 

Thời_hạn tước quyền sử_dụng giấy_phép , chứng_chỉ hành_nghề : tối_đa không quá 12 tháng đối_với hình_thức tước quyền sử_dụng có thời_hạn và từ 12 tháng trở lên đối_với hình_thức tước quyền sử_dụng không có thời_hạn . 

Đối_với loại giấy_phép mà người có thẩm_quyền xử_phạt VPHC không có thẩm_quyền tước quyền sử_dụng ( ví_dụ như Giấy_phép kinh_doanh do Sở Kế_hoạch & Đầu_tư các tỉnh , thành_phố cấp ) thì người có thẩm_quyền phải có văn_bản kiến_nghị đồng_thời gửi kèm theo hồ_sơ vụ_việc VPHC đến cơ_quan đã cấp phép để xử_lý . 

Đối_với hành_vi VPHC mà trong <NĐ rel="Reference"> Nghị_định 40/2009/NĐ-CP </NĐ> quy_định việc tước quyền sử_dụng giấy_phép , chứng_chỉ hành_nghề trong một khoảng thời_gian nhất_định ( ví_dụ từ 03 đến 06 tháng ) thì người có thẩm_quyền phải căn_cứ vào tính_chất , mức_độ của hành_vi vi_phạm để quyết_định thời_hạn cụ_thể người vi_phạm bị tước quyền sử_dụng giấy_phép , chứng_chỉ hành_nghề .
Nếu một người thực_hiện nhiều hành_vi vi_phạm mà các hành_vi vi_phạm này đều được quy_định hình_thức xử_phạt bổ_sung là tước quyền sử_dụng giấy_phép , chứng_chỉ hành_nghề thì người có thẩm_quyền xử_phạt chỉ áp_dụng tước quyền sử_dụng giấy_phép , chứng_chỉ hành_nghề đối_với một hành_vi vi_phạm mà <NĐ rel="Reference"> Nghị_định số 40/2009/NĐ-CP </NĐ> quy_định có thời_hạn tước quyền sử_dụng dài nhất đối_với hành_vi này .
b ) Tịch_thu tang_vật , phương_tiện VPHC : 

Tịch_thu tang_vật , phương_tiện VPHC là hình_thức phạt bổ_sung , được áp_dụng kèm theo hình_thức phạt chính . Thủ_tục và các trường_hợp cụ_thể bị áp_dụng tịch_thu tang_vật , phương_tiện vi_phạm được quy_định tại <NĐ rel="Reference"> Nghị_định số 40/2009/NĐ-CP </NĐ> và các Nghị_định xử_phạt VPHC trong lĩnh_vực quản_lý nhà_nước khác có liên_quan .
Khi tịch_thu tang_vật , phương_tiện VPHC , người có thẩm_quyền phải ra quyết_định tịch_thu theo mẫu quy_định tại Phụ_lục I ban_hành kèm theo Thông_tư này . 

Không áp_dụng hình_thức xử_phạt tịch_thu tang_vật , phương_tiện trong trường_hợp tang_vật , phương_tiện bị tổ_chức , cá_nhân vi_phạm chiếm_đoạt , sử_dụng trái_phép mà phải trả lại cho chủ sở_hữu hoặc người quản_lý , người sử_dụng hợp_pháp . 

c ) Các biện_pháp khắc_phục hậu_quả 

Biện_pháp khắc_phục hậu_quả là một trong nhiều hình_thức xử_phạt được áp_dụng cùng với hình_thức xử_phạt chính , nhằm xử_lý triệt_để vi_phạm , loại_trừ nguyên_nhân , điều_kiện tái_phạm , khắc_phục hậu_quả do VPHC gây ra . Việc áp_dụng biện_pháp khắc_phục hậu_quả buộc tiêu_hủy tang_vật VPHC phải lập hội_đồng tiêu_hủy và phải lập biên_bản tiêu_hủy theo mẫu tại Phụ_lục II ban_hành kèm theo Thông_tư này . Trong lĩnh_vực thú_y , ngoài các biện_pháp khắc_phục hậu_quả được quy_định tại khoản 3 , Điều 7 thì <NĐ rel="Reference"> Nghị_định số 40/2009/NĐ-CP </NĐ> còn quy_định một_số biện_pháp khắc_phục hậu_quả đặc_thù sau đây :
Tạm đình_chỉ hoạt_động của cơ_sở ; 

Buộc thu_hồi thuốc thú_y . 

Đối_với hành_vi vi_phạm_quy_định tại điểm a khoản 3 và khoản 4 Điều 17 <NĐ rel="Reference"> Nghị_định 40/2009/NĐ-CP </NĐ> quy_định biện_pháp khắc_phục hậu_quả là tạm đình_chỉ hoạt_động của cơ_sở trong trường_hợp cần_thiết để khắc_phục cho đến khi đủ điều_kiện vệ_sinh thú_y theo quy_định .
Trường_hợp cần_thiết được hiểu là các trường_hợp mà cơ_sở vi_phạm nghiêm_trọng các quy_định về điều_kiện vệ_sinh thú_y , vệ_sinh thú_y môi_trường sản_xuất , kinh_doanh mà hậu_quả có_thể gây ảnh_hưởng nặng_nề hoặc tác_động trực_tiếp đến sức_khỏe người dân hoặc môi_trường sống xung_quanh . 

Tùy theo mức_độ vi_phạm , tình_trạng vi_phạm điều_kiện vệ_sinh thú_y của cơ_sở mà người có thẩm_quyền xử_phạt quyết_định thời_gian tạm đình_chỉ hoạt_động của cơ_sở , đồng_thời nêu rõ thời_điểm cơ_sở phải khắc_phục hoàn_toàn điều_kiện vệ_sinh thú_y để cơ_quan thú_y có thẩm_quyền tiến_hành kiểm_tra trước khi cho phép cơ_sở hoạt_động trở_lại . 

Đối_với các hành_vi vi_phạm_quy_định tại khoản 2 Điều 18 , khoản 3 Điều 20 <NĐ rel="Reference"> Nghị_định 40/2009/NĐ-CP </NĐ> quy_định biện_pháp khắc_phục hậu_quả là buộc thu_hồi thuốc thú_y , nguyên_liệu làm thuốc thú_y .
Việc thu_hồi thuốc được thực_hiện theo quy_định tại <TT rel="Reference"> Thông_tư số 02/2009/TT-BNN ngày 14/01/2009 </TT> của Bộ Nông_nghiệp và PTNT hướng_dẫn thủ_tục thu_hồi và xử_lý thuốc thú_y .
Điều 13 .  Trách_nhiệm thi_hành 

1 . Thông_tư này có hiệu_lực sau 45 ngày , kể từ ngày ký ban_hành .  Những quy_định trước_đây trái với Thông_tư này đều bãi_bỏ . 

2 . Chánh Thanh_tra Sở Nông_nghiệp và Phát_triển nông_thôn , Chánh Thanh_tra Cục Thú_y , Chánh thanh_tra Chi_cục Thú_y các tỉnh , thành_phố chịu trách_nhiệm chỉ_đạo , hướng_dẫn , đôn_đốc , kiểm_tra việc thực_hiện Thông_tư này . 

3 . Trong quá_trình thực_hiện Thông_tư , nếu có vướng_mắc , cơ_quan , tổ_chức , cá_nhân phản_ánh về Bộ Nông_nghiệp và Phát_triển nông_thôn để kịp_thời điều_chỉnh , bổ_sung ./. 